Workbook

Sheet Energy Cost Analysis
D4: Energy Cost Analysis - Audited Power Cost Model
D8: Key Assumptions | G8: Unit | I8: Value (2026) | K8: Value (2036) | M8: Value (2051) | N8: Notes / Source Facts
D10: Arizona Ground Incident Solar Resource | G10: kWh/m2/day | I10: 6.52 | K10: 6.52 | M10: 6.52 | N10: From Sunlight-Analysis File - Winter flat one axis tracking panel (Arizona)
D11: SSO Incident Solar Resource | G11: kWh/m2/day | I11: 32.66 | K11: 32.66 | M11: 32.66 | N11: From Sunlight-Analysis File - Winter 500 km SSO in sun-track
D12: Ground Weather / Environment Factor | G12: x | I12: 0.9 | K12: 0.9 | M12: 0.9 | N12: Arizona winter weather, dust, sand, vegetation, etc.
D13: Firm Solar Battery Duration | G13: hours | I13: 14.4 | K13: 14.4 | M13: 14.4 | N13: 24/7 constant solar+battery storage output: 24h - 9.6h winter collection window.
D14: Space Array Hardware Cost | G14: $/m2 | I14: 330 | K14: 225 | M14: 214 | N14: Optimistic Estimate for light weight, vibe/vacuum/thermal/radiation engineered, extendable, SpaceX/Tesla built panels - 1.5X Ground Installed PV system cost as my reasonable bound
D15: Space Panel Useful Life | G15: years | I15: 5 | K15: 30 | M15: 30 | N15: 5 years assumption for non-modular AI-Sat-Mini due to outdated compute hardware. 30 year assumption for modular solar farm with replaceable compute modules.
D16: Space Battery Req. | G16: kWh/kW | I16: 0 | K16: 0 | M16: 0 | N16: Assuming high altitude SSO, very small battery required, assumed negligable
D20: Sourced Assumptions | G20: Unit | I20: Value (2026) | K20: Value (2036) | M20: Value (2051) | N20: Notes / Source Facts
D22: Source Projection Year | G22: year | I22: 2026 | K22: 2036 | M22: 2050 | N22: 2051 column uses 2050 where source projections stop. SF-ATB.
D23: Ground PV Installed System Cost | G23: $/m2 | I23: ='Model Detail'!C12 -> 220.14463 | K23: ='Model Detail'!D12 -> 170.97124 | M23: ='Model Detail'!E12 -> 142.69476 | N23: Derived from ATB $/kWac, ILR, and module efficiency. SF-ATB-PV/SF-DOE-PV.
D24: Ground PV Fixed O&M | G24: $/m2-yr | I24: ='Model Detail'!C14 -> 3.1353937 | K24: ='Model Detail'!D14 -> 2.8850916 | M24: ='Model Detail'!E14 -> 2.6670666 | N24: Derived from ATB $/kWac-yr and area per kWac. SF-ATB-PV.
D25: Ground PV STC Module Efficiency | G25: % | I25: 0.206 | K25: 0.26 | M25: 0.28 | N25: 2026 DOE benchmark; future values are analyst estimates anchored to ATB/ITRPV improvement direction. SF-DOE-PV/SF-ATB-PV.
D26: Ground Panel Effective Efficiency @ 55C | G26: % | I26: =I25*I27 -> 0.18746 | K26: =K25*K27 -> 0.2366 | M26: =M25*M27 -> 0.2548 | N26: Hot-operating effective efficiency after temperature derate.
D27: Ground Temperature Derate Factor | G27: x | I27: 0.91 | K27: 0.91 | M27: 0.91 | N27: Analyst estimate for hot Arizona operation; kept explicit. SF-DOE-PV/SF-ATB-PV.
D28: Ground Panel Degradation | G28: %/yr | I28: 0.007 | K28: 0.005 | M28: 0.002 | N28: ATB degradation pathway: 0.7% base, 0.5% moderate, 0.2% advanced. SF-ATB-PV.
D29: Ground PV Fixed Charge Rate | G29: %/yr | I29: 0.056638023 | K29: 0.056638023 | M29: 0.056638023 | N29: ATB UtilityPV Class 1 R&D 30-year fixed charge rate. SF-ATB-PV.
D30: 4h Battery CAPEX Reference | G30: $/kW | I30: 1659.3941 | K30: 1326.6147 | M30: 1035.7717 | N30: ATB 4-hour utility BESS CAPEX reference; firm solar case scales fixed costs by required duration. SF-ATB-BESS.
D31: 4h Battery Capital Fixed Cost Reference | G31: $/kW-yr | I31: 58.498224 | K31: 46.76683 | M31: 36.513813 | N31: ATB 4-hour utility BESS capital fixed cost reference; scaled by firm duration. SF-ATB-BESS.
D32: 4h Battery Fixed O&M Reference | G32: $/kW-yr | I32: 37.522398 | K32: 29.496197 | M32: 22.481448 | N32: ATB 4-hour utility BESS fixed O&M reference; scaled by firm duration. SF-ATB-BESS.
D33: Ground Battery Round-trip Efficiency | G33: % | I33: 0.85 | K33: 0.85 | M33: 0.85 | N33: ATB representative utility battery RTE; used to gross up PV energy and storage capacity in firm solar+BESS. SF-ATB-BESS.
D34: Space Panel Density | G34: kg/m2 | I34: 2.3 | K34: 2 | M34: 1.8 | N34: Analyst best-case lightweight array density, checked against NASA specific-power context. SF-NASA-POWER.
D35: Space Panel Net Efficiency @ 95C | G35: % | I35: 0.21 | K35: 0.24 | M35: 0.26 | N35: Lowered analyst estimate for SpaceX mass-produced, cost-optimized arrays operating hot in LEO. SF-SPACE-EFFICIENCY.
D36: Space Panel Degradation | G36: %/yr | I36: 0.015 | K36: 0.01 | M36: 0.007 | N36: Short LEO mission estimate; useful life is constrained by refresh/deorbit rather than theoretical panel life. SF-SPACEX.
D37: Space Battery Storage Cost | G37: $/kWh | I37: 200 | K37: 110 | M37: 80 | N37: Analyst placeholder; unused while Space Battery Req. is zero. SF-ATB-BESS/SF-NASA-POWER.
D41: Power Source LCOE / Cost Benchmarks | G41: Unit | I41: Value (2026) | K41: Value (2036) | M41: Value (2051) | N41: Notes / Source Facts
D43: Nuclear Existing LCOE Proxy | G43: $/kWh | I43: 0.034 | K43: 0.036 | M43: 0.038 | N43: Existing fleet operating-cost proxy; not a new-build LCOE. SF-LAZARD.
D44: Nuclear New Build LCOE | G44: $/kWh | I44: 0.088 | K44: 0.092 | M44: 0.071 | N44: New-build/advanced nuclear benchmark. SF-EIA/SF-ATB.
D45: Nat Gas Existing LCOE Proxy | G45: $/kWh | I45: 0.032 | K45: 0.038 | M45: 0.04 | N45: Existing CCGT operating-cost proxy. SF-LAZARD.
D46: Nat Gas New Build LCOE | G46: $/kWh | I46: 0.077 | K46: 0.07 | M46: 0.065 | N46: New-build combined-cycle benchmark. SF-EIA/SF-LAZARD.
D47: Coal Existing LCOE Proxy | G47: $/kWh | I47: 0.073 | K47: 0.08 | M47: 0.085 | N47: Existing coal operating-cost proxy. SF-LAZARD.
D48: Coal New Build LCOE | G48: $/kWh | I48: 0.122 | K48: 0.115 | M48: 0.105 | N48: Comparative new-build coal value; unlikely U.S. base-case build. SF-EIA/SF-LAZARD.
D49: Wind Existing LCOE Proxy | G49: $/kWh | I49: 0.035 | K49: 0.03 | M49: 0.027 | N49: Existing/new contracted U.S. wind proxy. SF-LAZARD.
D50: Wind New Build LCOE | G50: $/kWh | I50: 0.029810344 | K50: 0.025121455 | M50: 0.021348398 | N50: ATB land-based wind Class 4 Moderate R&D 30-year LCOE. SF-ATB-WIND.
D51: Wind + 4h Battery New Build LCOE | G51: $/kWh | I51: ='Model Detail'!C33 -> 0.053547829 | K51: ='Model Detail'!D33 -> 0.043344397 | M51: ='Model Detail'!E33 -> 0.035288245 | N51: Wind LCOE plus comparable 4-hour BESS cost adder. SF-ATB-WIND/SF-ATB-BESS.
D52: Hydro Existing LCOE Proxy | G52: $/kWh | I52: ='Model Detail'!C36 -> 0.0318251 | K52: ='Model Detail'!D36 -> 0.0318251 | M52: ='Model Detail'!E36 -> 0.0304414 | N52: Hydro existing O&M proxy from ATB FOM and CF, excluding sunk capex. SF-ATB-HYDRO.
D53: Hydro New Build LCOE | G53: $/kWh | I53: 0.098832401 | K53: 0.098832401 | M53: 0.094764008 | N53: ATB Hydropower NPD1 Moderate R&D 30-year LCOE. SF-ATB-HYDRO.
D54: Ground Solar (Arizona) New Build LCOE | G54: $/kWh | I54: ='Model Detail'!C21 -> 0.042951312 | K54: ='Model Detail'!D21 -> 0.026646775 | M54: ='Model Detail'!E21 -> 0.020273478 | N54: Calculated from 6.52 kWh/m2/day resource, efficiency, weather/environment factor, capex, O&M, and FCR.
D55: Ground Solar + Firm Battery (Arizona) New Build LCOE | G55: $/kWh | I55: ='Model Detail'!C29 -> 0.09392325 | K55: ='Model Detail'!D29 -> 0.066339927 | M55: ='Model Detail'!E29 -> 0.050943173 | N55: Calculated PV LCOE plus firm daily-shift BESS sized for 24/7 constant output.
D56: NREL PV+BESS 4h Benchmark (not model driver) | G56: $/kWh | I56: 0.06904 | K56: 0.04996 | M56: 0.04126 | N56: ATB PV+BESS Class 1 4-hour benchmark shown only as cross-check. Not used in break-even formulas. SF-ATB-PVBESS.
D57: China Solar+BESS LCOE (separate) | G57: $/kWh | I57: 0.055 | K57: 0.039 | M57: 0.032 | N57: China-only comparison. Excluded from U.S. cheapest-source logic. SF-IRENA/IEA.
D61: Results | G61: Unit | I61: Value (2026) | K61: Value (2036) | M61: Value (2051) | N61: Notes
D63: Space Solar Cost (after deployment, excl. launch) | G63: $/kWh | I63: ='Model Detail'!C50 -> 0.027167141 | K63: ='Model Detail'!D50 -> 0.0030212641 | M63: ='Model Detail'!E50 -> 0.0025435693 | N63: Power hardware cost divided by lifetime delivered SSO kWh after deployment.
D64: Break Even Launch Cost vs. Ground Solar+Firm Battery (Arizona) | G64: $/kg | I64: ='Model Detail'!C51 -> 352.56012 | K64: ='Model Detail'!D51 -> 2357.7382 | M64: ='Model Detail'!E51 -> 2262.2443 | N64: Launch $/kg that makes orbital power equal calculated Arizona firm solar+BESS.
D65: Break Even Launch Cost vs. Ground Solar+BESS (China) | G65: $/kg | I65: ='Model Detail'!C52 -> 146.99413 | K65: ='Model Detail'!D52 -> 1339.7067 | M65: ='Model Detail'!E52 -> 1376.8221 | N65: China result shown separately; excluded from U.S. cheapest-source logic.
D66: Break Even Launch Cost vs. Cheapest New Build Power Source (US) | G66: $/kg | I66: ='Model Detail'!C53 -> 139.32475 | K66: ='Model Detail'!D53 -> 1501.475 | M66: ='Model Detail'!E53 -> 1530.5178 | N66: Cheapest U.S. new-build LCOE rows only; standalone wind and solar excluded.
D67: Cheapest New Build Power Source (US) | G67: name | I67: ='Model Detail'!C54 -> Wind+BESS | K67: ='Model Detail'!D54 -> Wind+BESS | M67: ='Model Detail'!E54 -> Wind+BESS | N67: China, benchmark-only rows, standalone wind, and standalone solar excluded.
D68: Break Even Launch Cost vs. Cheapest Existing Power Source (US) | G68: $/kg | I68: ='Model Detail'!C55 -> 24.600156 | K68: ='Model Detail'!D55 -> 1072.5417 | M68: ='Model Detail'!E55 -> 1303.9716 | N68: Cheapest U.S. existing-source proxy rows only; standalone wind excluded.
D69: Cheapest Existing Power Source (US) | G69: name | I69: ='Model Detail'!C56 -> Hydro | K69: ='Model Detail'!D56 -> Hydro | M69: ='Model Detail'!E56 -> Hydro | N69: Existing proxies exclude China, new-build rows, and standalone wind.
O72: Year | P72: Space Solar ($/MWh) | Q72: AZ Firm Solar+BESS ($/MWh) | R72: Wind+BESS ($/MWh) | S72: Cheapest Existing US ($/MWh)
O73: 2026 | P73: =I63*1000 -> 27.167141 | Q73: =I55*1000 -> 93.92325 | R73: =I51*1000 -> 53.547829 | S73: ='Model Detail'!C38*1000 -> 31.8251
O74: 2036 | P74: =K63*1000 -> 3.0212641 | Q74: =K55*1000 -> 66.339927 | R74: =K51*1000 -> 43.344397 | S74: ='Model Detail'!D38*1000 -> 31.8251
O75: 2051 | P75: =M63*1000 -> 2.5435693 | Q75: =M55*1000 -> 50.943173 | R75: =M51*1000 -> 35.288245 | S75: ='Model Detail'!E38*1000 -> 30.4414
D110: Year | E110: Space Solar ($/MWh) | F110: AZ Firm Solar+BESS ($/MWh) | G110: Wind+BESS ($/MWh) | H110: Cheapest Existing US ($/MWh) | I110: Nat Gas New Build ($/MWh)
D111: 2026 | E111: =I63*1000 -> 27.167141 | F111: =I55*1000 -> 93.92325 | G111: =I51*1000 -> 53.547829 | H111: =MIN(I43,I45,I47,I52)*1000 -> 31.8251 | I111: =I46*1000 -> 77
D112: 2036 | E112: =K63*1000 -> 3.0212641 | F112: =K55*1000 -> 66.339927 | G112: =K51*1000 -> 43.344397 | H112: =MIN(K43,K45,K47,K52)*1000 -> 31.8251 | I112: =K46*1000 -> 70
D113: 2051 | E113: =M63*1000 -> 2.5435693 | F113: =M55*1000 -> 50.943173 | G113: =M51*1000 -> 35.288245 | H113: =MIN(M43,M45,M47,M52)*1000 -> 30.4414 | I113: =M46*1000 -> 65

Sheet TCO Analysis
D4: TCO Analysis - AI Satellite vs. Terrestrial Datacenter
D5: Annualized rack/satellite TCO comparison. User-specific TCO assumptions are intentionally blank; linked power costs flow from the Energy Cost Analysis sheet.
D8: Key Assumptions (AI Satellite) | G8: Unit | I8: Value (2026) | K8: Value (2036) | M8: Value (2051) | N8: Notes
D10: AI Satellite IT Power | G10: kW | I10: 100 | K10: 100 | M10: 100 | N10: User input. Satellite and rack power may differ; results normalize to IT kW.
D11: IT Hardware Mass | G11: kg | I11: 500 | K11: 500 | M11: 500 | N11: User input.
D12: Structural/Cooling Mass | G12: kg | I12: 1000 | K12: 800 | M12: 600 | N12: User input.
D13: Bus Components Mass | G13: kg | I13: 50 | K13: 50 | M13: 50 | N13: User input.
D14: Useful Life of IT Hardware | G14: years | I14: 5 | K14: 5 | M14: 5 | N14: User input.
D15: Useful Life of Bus/Cooling | G15: years | I15: 5 | K15: 5 | M15: 5 | N15: User input; used for structural/cooling and bus annualization.
D16: Cost of IT Hardware | G16: $/sat | I16: =1.3*I35*100/132 -> 3840909.1 | K16: =1.3*K35*100/132 -> 7878787.9 | M16: =1.3*M35*100/132 -> 19696970 | N16: User input.
D17: Cost of Structural/Cooling/Assembly | G17: $/sat | I17: 500000 | K17: 300000 | M17: 200000 | N17: User input.
D18: Cost of Bus Components | G18: $/sat | I18: 200000 | K18: 175000 | M18: 150000 | N18: User input.
D19: PUE | G19: x | I19: 1.05 | K19: 1.05 | M19: 1.05 | N19: User input.
D20: Opex | G20: $/yr | I20: 30000 | K20: 25000 | M20: 20000 | N20: User input.
D21: Starlink Networking Opportunity Cost | G21: $/yr | I21: 0 | K21: 0 | M21: 0 | N21: User input.
D22: Launch Cost Assumption | G22: $/kg | I22: 1363 | K22: 600 | M22: 200 | N22: User input; included in pie-chart TCO, excluded from breakeven formula.
D25: Key Assumptions (Terrestrial Datacenter) | G25: Unit | I25: Value (2026) | K25: Value (2036) | M25: Value (2051) | N25: Notes
D27: Terrestrial Power Source | G27: source | I27: Nat Gas New Build | K27: Nat Gas New Build | M27: Nat Gas New Build | N27: Dropdown. Selected source drives terrestrial power LCOE.
D28: Terrestrial Rack IT Power | G28: kW | I28: 132 | K28: 132 | M28: 132 | N28: User input. May differ from satellite IT power.
D29: PUE | G29: x | I29: 1.1 | K29: 1.08 | M29: 1.06 | N29: User input.
D30: Datacenter Costs | G30: $/rack | I30: 1320000 | K30: 1250000 | M30: 1200000 | N30: User input; excludes IT hardware and cooling hardware to avoid double-counting.
D31: Useful Life of Datacenter | G31: years | I31: 30 | K31: 30 | M31: 30 | N31: User input.
D32: Cooling Costs | G32: $/rack | I32: 250000 | K32: 180000 | M32: 150000 | N32: User input.
D33: Useful Life of Cooling Hardware | G33: years | I33: 10 | K33: 10 | M33: 10 | N33: User input.
D34: Opex | G34: $/yr | I34: 90000 | K34: 80000 | M34: 70000 | N34: User input.
D35: Cost of IT Hardware | G35: $/rack | I35: 3900000 | K35: 8000000 | M35: 20000000 | N35: User input.
D36: Useful Life of IT Hardware | G36: years | I36: 5 | K36: 5 | M36: 5 | N36: User input.
D38: Derived / Linked Assumptions | G38: Unit | I38: Value (2026) | K38: Value (2036) | M38: Value (2051) | N38: Notes / Source
D40: Selected Terrestrial Power LCOE | G40: $/kWh | I40: =IFERROR(INDEX($K$153:$K$168,MATCH(I27,$J$153:$J$168,0)),"") -> 0.077 | K40: =IFERROR(INDEX($L$153:$L$168,MATCH(K27,$J$153:$J$168,0)),"") -> 0.07 | M40: =IFERROR(INDEX($M$153:$M$168,MATCH(M27,$J$153:$J$168,0)),"") -> 0.065 | N40: Selected by terrestrial power-source dropdown.
D41: Space Solar Cost excl. Launch | G41: $/kWh | I41: ='Energy Cost Analysis'!I63 -> 0.027167141 | K41: ='Energy Cost Analysis'!K63 -> 0.0030212641 | M41: ='Energy Cost Analysis'!M63 -> 0.0025435693 | N41: Linked from Energy Cost Analysis row 63.
D42: Space Panel Density | G42: kg/m2 | I42: ='Energy Cost Analysis'!I34 -> 2.3 | K42: ='Energy Cost Analysis'!K34 -> 2 | M42: ='Energy Cost Analysis'!M34 -> 1.8 | N42: Linked from Energy Cost Analysis row 34.
D43: Space Power Useful Life | G43: years | I43: ='Energy Cost Analysis'!I15 -> 5 | K43: ='Energy Cost Analysis'!K15 -> 30 | M43: ='Energy Cost Analysis'!M15 -> 30 | N43: Linked from Energy Cost Analysis row 15.
D44: Space Panel Net Efficiency | G44: % | I44: ='Energy Cost Analysis'!I35 -> 0.21 | K44: ='Energy Cost Analysis'!K35 -> 0.24 | M44: ='Energy Cost Analysis'!M35 -> 0.26 | N44: Linked from Energy Cost Analysis row 35.
D45: SSO Incident Solar Resource | G45: kWh/m2/day | I45: ='Energy Cost Analysis'!I11 -> 32.66 | K45: ='Energy Cost Analysis'!K11 -> 32.66 | M45: ='Energy Cost Analysis'!M11 -> 32.66 | N45: Linked from Energy Cost Analysis row 11.
D46: Satellite Facility Power incl. PUE | G46: kW | I46: =IF(OR(I10="",I19=""),"",I10*I19) -> 105 | K46: =IF(OR(K10="",K19=""),"",K10*K19) -> 105 | M46: =IF(OR(M10="",M19=""),"",M10*M19) -> 105 | N46: Satellite IT load grossed up by PUE.
D47: Satellite Solar Array Area Required | G47: m2 | I47: =IF(OR(I46="",I45="",I44=""),"",I46/(I45/24*I44)) -> 367.42192 | K47: =IF(OR(K46="",K45="",K44=""),"",K46/(K45/24*K44)) -> 321.49418 | M47: =IF(OR(M46="",M45="",M44=""),"",M46/(M45/24*M44)) -> 296.76386 | N47: Average power area from SSO daily incident energy and panel net efficiency.
D48: Space Power Hardware Mass | G48: kg | I48: =IF(OR(I47="",I42=""),"",I47*I42) -> 845.07042 | K48: =IF(OR(K47="",K42=""),"",K47*K42) -> 642.98836 | M48: =IF(OR(M47="",M42=""),"",M47*M42) -> 534.17495 | N48: Solar-array mass needed for launch mass annualization.
D49: Satellite Total Launch Mass | G49: kg | I49: =IF(OR(I11="",I12="",I13="",I48=""),"",I11+I12+I13+I48) -> 2395.0704 | K49: =IF(OR(K11="",K12="",K13="",K48=""),"",K11+K12+K13+K48) -> 1992.9884 | M49: =IF(OR(M11="",M12="",M13="",M48=""),"",M11+M12+M13+M48) -> 1684.1749 | N49: IT + structural/cooling + bus + derived power hardware mass.
D50: Annualized Launch Mass | G50: kg/yr | I50: =IF(OR(I11="",I12="",I13="",I14="",I15="",I43="",I48="",I14=0,I15=0,I43=0),"",I11/I14+I12/I15+I13/I15+I48/I43) -> 479.01408 | K50: =IF(OR(K11="",K12="",K13="",K14="",K15="",K43="",K48="",K14=0,K15=0,K43=0),"",K11/K14+K12/K15+K13/K15+K48/K43) -> 291.43295 | M50: =IF(OR(M11="",M12="",M13="",M14="",M15="",M43="",M48="",M14=0,M15=0,M43=0),"",M11/M14+M12/M15+M13/M15+M48/M43) -> 247.80583 | N50: Replacement-rate launch mass; power hardware uses linked space power useful life.
D51: Satellite Annual Energy Use | G51: kWh/yr | I51: =IF(OR(I46=""),"",I46*8760) -> 919800 | K51: =IF(OR(K46=""),"",K46*8760) -> 919800 | M51: =IF(OR(M46=""),"",M46*8760) -> 919800 | N51: Satellite facility power times 8,760.
D52: Terrestrial Facility Power incl. PUE | G52: kW | I52: =IF(OR(I28="",I29=""),"",I28*I29) -> 145.2 | K52: =IF(OR(K28="",K29=""),"",K28*K29) -> 142.56 | M52: =IF(OR(M28="",M29=""),"",M28*M29) -> 139.92 | N52: Rack IT load grossed up by PUE.
D53: Terrestrial Annual Energy Use | G53: kWh/yr | I53: =IF(OR(I52=""),"",I52*8760) -> 1271952 | K53: =IF(OR(K52=""),"",K52*8760) -> 1248825.6 | M53: =IF(OR(M52=""),"",M52*8760) -> 1225699.2 | N53: Terrestrial facility power times 8,760.
D54: Satellite Power Cost excl. Launch | G54: $/yr | I54: =IF(OR(I51="",I41=""),"",I51*I41) -> 24988.336 | K54: =IF(OR(K51="",K41=""),"",K51*K41) -> 2778.9587 | M54: =IF(OR(M51="",M41=""),"",M51*M41) -> 2339.575 | N54: Uses linked space solar LCOE excluding launch.
D55: Terrestrial Selected Power Cost | G55: $/yr | I55: =IF(OR(I53="",I40=""),"",I53*I40) -> 97940.304 | K55: =IF(OR(K53="",K40=""),"",K53*K40) -> 87417.792 | M55: =IF(OR(M53="",M40=""),"",M53*M40) -> 79670.448 | N55: Uses selected terrestrial power-source LCOE.
D56: Satellite Launch Cost @ Assumption | G56: $/yr | I56: =IF(OR(ISBLANK(I22),NOT(ISNUMBER(I50)),I50=0),"",I22*I50) -> 652896.2 | K56: =IF(OR(ISBLANK(K22),NOT(ISNUMBER(K50)),K50=0),"",K22*K50) -> 174859.77 | M56: =IF(OR(ISBLANK(M22),NOT(ISNUMBER(M50)),M50=0),"",M22*M50) -> 49561.166 | N56: Included in pie chart TCO only when launch input is filled.
D57: Satellite Annual TCO excl. Launch | G57: $/yr | I57: =IF(OR(ISBLANK(I16),ISBLANK(I14),ISBLANK(I17),ISBLANK(I15),ISBLANK(I18),NOT(ISNUMBER(I54)),ISBLANK(I20),ISBLANK(I21),I14=0,I15=0),"",I16/I14+I17/I15+I18/I15+I54+I20+I21) -> 963170.15 | K57: =IF(OR(ISBLANK(K16),ISBLANK(K14),ISBLANK(K17),ISBLANK(K15),ISBLANK(K18),NOT(ISNUMBER(K54)),ISBLANK(K20),ISBLANK(K21),K14=0,K15=0),"",K16/K14+K17/K15+K18/K15+K54+K20+K21) -> 1698536.5 | M57: =IF(OR(ISBLANK(M16),ISBLANK(M14),ISBLANK(M17),ISBLANK(M15),ISBLANK(M18),NOT(ISNUMBER(M54)),ISBLANK(M20),ISBLANK(M21),M14=0,M15=0),"",M16/M14+M17/M15+M18/M15+M54+M20+M21) -> 4031733.5 | N57: Used for breakeven launch cost; excludes launch assumption.
D58: Satellite Annual TCO incl. Launch | G58: $/yr | I58: =IF(OR(NOT(ISNUMBER(I57)),NOT(ISNUMBER(I56))),"",I57+I56) -> 1616066.4 | K58: =IF(OR(NOT(ISNUMBER(K57)),NOT(ISNUMBER(K56))),"",K57+K56) -> 1873396.3 | M58: =IF(OR(NOT(ISNUMBER(M57)),NOT(ISNUMBER(M56))),"",M57+M56) -> 4081294.7 | N58: Shown beside satellite pie charts.
D59: Terrestrial Annual TCO | G59: $/yr | I59: =IF(OR(ISBLANK(I35),ISBLANK(I36),ISBLANK(I30),ISBLANK(I31),ISBLANK(I32),ISBLANK(I33),NOT(ISNUMBER(I55)),ISBLANK(I34),I31=0,I33=0,I36=0),"",I35/I36+I30/I31+I32/I33+I55+I34) -> 1036940.3 | K59: =IF(OR(ISBLANK(K35),ISBLANK(K36),ISBLANK(K30),ISBLANK(K31),ISBLANK(K32),ISBLANK(K33),NOT(ISNUMBER(K55)),ISBLANK(K34),K31=0,K33=0,K36=0),"",K35/K36+K30/K31+K32/K33+K55+K34) -> 1827084.5 | M59: =IF(OR(ISBLANK(M35),ISBLANK(M36),ISBLANK(M30),ISBLANK(M31),ISBLANK(M32),ISBLANK(M33),NOT(ISNUMBER(M55)),ISBLANK(M34),M31=0,M33=0,M36=0),"",M35/M36+M30/M31+M32/M33+M55+M34) -> 4204670.4 | N59: Shown beside terrestrial pie charts.
D62: Results | G62: Unit | I62: Value (2026) | K62: Value (2036) | M62: Value (2051) | N62: Notes
D64: Satellite Total Annual TCO incl. Launch | G64: $/yr | I64: =IF(ISNUMBER(I58),I58,"Inputs pending") -> 1616066.4 | K64: =IF(ISNUMBER(K58),K58,"Inputs pending") -> 1873396.3 | M64: =IF(ISNUMBER(M58),M58,"Inputs pending") -> 4081294.7 | N64: Includes launch cost assumption.
D65: Satellite TCO incl. Launch | G65: $/IT kW-yr | I65: =IF(OR(NOT(ISNUMBER(I58)),ISBLANK(I10),I10=0),"Inputs pending",I58/I10) -> 16160.664 | K65: =IF(OR(NOT(ISNUMBER(K58)),ISBLANK(K10),K10=0),"Inputs pending",K58/K10) -> 18733.963 | M65: =IF(OR(NOT(ISNUMBER(M58)),ISBLANK(M10),M10=0),"Inputs pending",M58/M10) -> 40812.947 | N65: Normalized by satellite IT power.
D66: Satellite TCO incl. Launch | G66: $/W-yr | I66: =IF(OR(NOT(ISNUMBER(I58)),ISBLANK(I10),I10=0),"Inputs pending",I58/(I10*1000)) -> 16.160664 | K66: =IF(OR(NOT(ISNUMBER(K58)),ISBLANK(K10),K10=0),"Inputs pending",K58/(K10*1000)) -> 18.733963 | M66: =IF(OR(NOT(ISNUMBER(M58)),ISBLANK(M10),M10=0),"Inputs pending",M58/(M10*1000)) -> 40.812947 | N66: Normalized by satellite IT watts.
D67: Terrestrial Total Annual TCO | G67: $/yr | I67: =IF(ISNUMBER(I59),I59,"Inputs pending") -> 1036940.3 | K67: =IF(ISNUMBER(K59),K59,"Inputs pending") -> 1827084.5 | M67: =IF(ISNUMBER(M59),M59,"Inputs pending") -> 4204670.4 | N67: Annualized rack/datacenter TCO.
D68: Terrestrial TCO | G68: $/IT kW-yr | I68: =IF(OR(NOT(ISNUMBER(I59)),ISBLANK(I28),I28=0),"Inputs pending",I59/I28) -> 7855.6084 | K68: =IF(OR(NOT(ISNUMBER(K59)),ISBLANK(K28),K28=0),"Inputs pending",K59/K28) -> 13841.549 | M68: =IF(OR(NOT(ISNUMBER(M59)),ISBLANK(M28),M28=0),"Inputs pending",M59/M28) -> 31853.564 | N68: Normalized by terrestrial rack IT power.
D69: Terrestrial TCO | G69: $/W-yr | I69: =IF(OR(NOT(ISNUMBER(I59)),ISBLANK(I28),I28=0),"Inputs pending",I59/(I28*1000)) -> 7.8556084 | K69: =IF(OR(NOT(ISNUMBER(K59)),ISBLANK(K28),K28=0),"Inputs pending",K59/(K28*1000)) -> 13.841549 | M69: =IF(OR(NOT(ISNUMBER(M59)),ISBLANK(M28),M28=0),"Inputs pending",M59/(M28*1000)) -> 31.853564 | N69: Normalized by terrestrial rack IT watts.
D70: Breakeven Launch Cost excl. Launch Assumption (full TCO) | G70: $/kg | I70: =IF(OR(NOT(ISNUMBER(I59)),ISBLANK(I28),I28=0,NOT(ISNUMBER(I57)),ISBLANK(I10),I10=0,NOT(ISNUMBER(I50)),I50=0),"Inputs pending",((I59/I28)-(I57/I10))*I10/I50) -> -370.78099 | K70: =IF(OR(NOT(ISNUMBER(K59)),ISBLANK(K28),K28=0,NOT(ISNUMBER(K57)),ISBLANK(K10),K10=0,NOT(ISNUMBER(K50)),K50=0),"Inputs pending",((K59/K28)-(K57/K10))*K10/K50) -> -1078.7443 | M70: =IF(OR(NOT(ISNUMBER(M59)),ISBLANK(M28),M28=0,NOT(ISNUMBER(M57)),ISBLANK(M10),M10=0,NOT(ISNUMBER(M50)),M50=0),"Inputs pending",((M59/M28)-(M57/M10))*M10/M50) -> -3415.4851 | N70: Can be negative; compares full annualized terrestrial TCO vs. satellite TCO excluding launch on a normalized IT-kW basis.
D71: Satellite Chart Status | G71: status | I71: =IF(ISNUMBER(I58),"Ready","Inputs pending") -> Ready | K71: =IF(ISNUMBER(K58),"Ready","Inputs pending") -> Ready | M71: =IF(ISNUMBER(M58),"Ready","Inputs pending") -> Ready | N71: Pie chart uses a neutral pending slice until all incl.-launch inputs are filled.
D72: Terrestrial Chart Status | G72: status | I72: =IF(ISNUMBER(I59),"Ready","Inputs pending") -> Ready | K72: =IF(ISNUMBER(K59),"Ready","Inputs pending") -> Ready | M72: =IF(ISNUMBER(M59),"Ready","Inputs pending") -> Ready | N72: Pie chart uses a neutral pending slice until all terrestrial inputs are filled.
D75: TCO Pie Charts and Total Costs
I78: AI Satellite TCO - 2026 | J78: AI Satellite TCO - 2026 | K78: AI Satellite TCO - 2026 | Q78: Terrestrial Datacenter TCO - 2026 | R78: Terrestrial Datacenter TCO - 2026 | S78: Terrestrial Datacenter TCO - 2026
I79: Total Annual TCO incl. Launch | K79: =IF(ISNUMBER(I58),I58,"Inputs pending") -> 1616066.4 | Q79: Total Annual TCO | S79: =IF(ISNUMBER(I59),I59,"Inputs pending") -> 1036940.3
I80: $/IT kW-year | K80: =IF(OR(NOT(ISNUMBER(I58)),ISBLANK(I10),I10=0),"Inputs pending",I58/I10) -> 16160.664 | Q80: $/IT kW-year | S80: =IF(OR(NOT(ISNUMBER(I59)),ISBLANK(I28),I28=0),"Inputs pending",I59/I28) -> 7855.6084
I81: $/W-year | K81: =IF(OR(NOT(ISNUMBER(I58)),ISBLANK(I10),I10=0),"Inputs pending",I58/(I10*1000)) -> 16.160664 | Q81: $/W-year | S81: =IF(OR(NOT(ISNUMBER(I59)),ISBLANK(I28),I28=0),"Inputs pending",I59/(I28*1000)) -> 7.8556084
I82: Launch Assumption | K82: =IF(ISBLANK(I22),"Inputs pending",I22) -> 1363 | Q82: Power Source | S82: =I27 -> Nat Gas New Build
I83: Breakeven Launch Cost (full TCO) | J83: Breakeven Launch Cost (full TCO) | K83: =IF(I70="Inputs pending","Inputs pending",I70) -> -370.78099 | Q83: Power LCOE | S83: =I40 -> 0.077
I84: Status | K84: =IF(ISNUMBER(I58),"Ready","Inputs pending") -> Ready | Q84: Status | S84: =IF(ISNUMBER(I59),"Ready","Inputs pending") -> Ready
I100: AI Satellite TCO - 2036 | J100: AI Satellite TCO - 2036 | K100: AI Satellite TCO - 2036 | Q100: Terrestrial Datacenter TCO - 2036 | R100: Terrestrial Datacenter TCO - 2036 | S100: Terrestrial Datacenter TCO - 2036
I101: Total Annual TCO incl. Launch | K101: =IF(ISNUMBER(K58),K58,"Inputs pending") -> 1873396.3 | Q101: Total Annual TCO | S101: =IF(ISNUMBER(K59),K59,"Inputs pending") -> 1827084.5
I102: $/IT kW-year | K102: =IF(OR(NOT(ISNUMBER(K58)),ISBLANK(K10),K10=0),"Inputs pending",K58/K10) -> 18733.963 | Q102: $/IT kW-year | S102: =IF(OR(NOT(ISNUMBER(K59)),ISBLANK(K28),K28=0),"Inputs pending",K59/K28) -> 13841.549
I103: $/W-year | K103: =IF(OR(NOT(ISNUMBER(K58)),ISBLANK(K10),K10=0),"Inputs pending",K58/(K10*1000)) -> 18.733963 | Q103: $/W-year | S103: =IF(OR(NOT(ISNUMBER(K59)),ISBLANK(K28),K28=0),"Inputs pending",K59/(K28*1000)) -> 13.841549
I104: Launch Assumption | K104: =IF(ISBLANK(K22),"Inputs pending",K22) -> 600 | Q104: Power Source | S104: =K27 -> Nat Gas New Build
I105: Breakeven Launch Cost (full TCO) | J105: Breakeven Launch Cost (full TCO) | K105: =IF(K70="Inputs pending","Inputs pending",K70) -> -1078.7443 | Q105: Power LCOE | S105: =K40 -> 0.07
I106: Status | K106: =IF(ISNUMBER(K58),"Ready","Inputs pending") -> Ready | Q106: Status | S106: =IF(ISNUMBER(K59),"Ready","Inputs pending") -> Ready
I122: AI Satellite TCO - 2051 | J122: AI Satellite TCO - 2051 | K122: AI Satellite TCO - 2051 | Q122: Terrestrial Datacenter TCO - 2051 | R122: Terrestrial Datacenter TCO - 2051 | S122: Terrestrial Datacenter TCO - 2051
I123: Total Annual TCO incl. Launch | K123: =IF(ISNUMBER(M58),M58,"Inputs pending") -> 4081294.7 | Q123: Total Annual TCO | S123: =IF(ISNUMBER(M59),M59,"Inputs pending") -> 4204670.4
I124: $/IT kW-year | K124: =IF(OR(NOT(ISNUMBER(M58)),ISBLANK(M10),M10=0),"Inputs pending",M58/M10) -> 40812.947 | Q124: $/IT kW-year | S124: =IF(OR(NOT(ISNUMBER(M59)),ISBLANK(M28),M28=0),"Inputs pending",M59/M28) -> 31853.564
I125: $/W-year | K125: =IF(OR(NOT(ISNUMBER(M58)),ISBLANK(M10),M10=0),"Inputs pending",M58/(M10*1000)) -> 40.812947 | Q125: $/W-year | S125: =IF(OR(NOT(ISNUMBER(M59)),ISBLANK(M28),M28=0),"Inputs pending",M59/(M28*1000)) -> 31.853564
I126: Launch Assumption | K126: =IF(ISBLANK(M22),"Inputs pending",M22) -> 200 | Q126: Power Source | S126: =M27 -> Nat Gas New Build
I127: Breakeven Launch Cost (full TCO) | J127: Breakeven Launch Cost (full TCO) | K127: =IF(M70="Inputs pending","Inputs pending",M70) -> -3415.4851 | Q127: Power LCOE | S127: =M40 -> 0.065
I128: Status | K128: =IF(ISNUMBER(M58),"Ready","Inputs pending") -> Ready | Q128: Status | S128: =IF(ISNUMBER(M59),"Ready","Inputs pending") -> Ready
D145: TCO Source / Audit Notes
D146: User TCO inputs | G146: Blank / User-filled | N146: Rack/satellite TCO assumptions remain user inputs; existing entries are preserved.
D147: Power source dropdown | G147: Dropdown | N147: Terrestrial Power Source uses an Excel list validation backed by the options table below the dashboard.
D148: TCO breakeven | G148: Full TCO | N148: Breakeven launch can be negative and compares full annualized TCO excluding launch, not power cost alone.
D149: TCO chart rebuild | G149: Filled years | N149: v013 rebuilds all 2026/2036/2051 TCO pie source ranges from current filled assumptions.
D152: TCO Chart Source Data | E152: TCO Chart Source Data | F152: TCO Chart Source Data | G152: TCO Chart Source Data | H152: TCO Chart Source Data | J152: Power Source | K152: 2026 LCOE | L152: 2036 LCOE | M152: 2051 LCOE
J153: Cheapest New Build (US) | K153: =MIN('Energy Cost Analysis'!I44,'Energy Cost Analysis'!I46,'Energy Cost Analysis'!I48,'Energy Cost Analysis'!I51,'Energy Cost Analysis'!I53,'Energy Cost Analysis'!I55) -> 0.053547829 | L153: =MIN('Energy Cost Analysis'!K44,'Energy Cost Analysis'!K46,'Energy Cost Analysis'!K48,'Energy Cost Analysis'!K51,'Energy Cost Analysis'!K53,'Energy Cost Analysis'!K55) -> 0.043344397 | M153: =MIN('Energy Cost Analysis'!M44,'Energy Cost Analysis'!M46,'Energy Cost Analysis'!M48,'Energy Cost Analysis'!M51,'Energy Cost Analysis'!M53,'Energy Cost Analysis'!M55) -> 0.035288245
D154: Category | E154: Annual Cost | G154: Category | H154: Annual Cost | J154: Cheapest Existing (US) | K154: =MIN('Energy Cost Analysis'!I43,'Energy Cost Analysis'!I45,'Energy Cost Analysis'!I47,'Energy Cost Analysis'!I52) -> 0.0318251 | L154: =MIN('Energy Cost Analysis'!K43,'Energy Cost Analysis'!K45,'Energy Cost Analysis'!K47,'Energy Cost Analysis'!K52) -> 0.0318251 | M154: =MIN('Energy Cost Analysis'!M43,'Energy Cost Analysis'!M45,'Energy Cost Analysis'!M47,'Energy Cost Analysis'!M52) -> 0.0304414
D155: IT Hardware | E155: =I16/I14 -> 768181.82 | G155: IT Hardware | H155: =I35/I36 -> 780000 | J155: Nuclear Existing | K155: ='Energy Cost Analysis'!I43 -> 0.034 | L155: ='Energy Cost Analysis'!K43 -> 0.036 | M155: ='Energy Cost Analysis'!M43 -> 0.038
D156: Struct/Cooling | E156: =I17/I15 -> 100000 | G156: Datacenter Facility | H156: =I30/I31 -> 44000 | J156: Nuclear New Build | K156: ='Energy Cost Analysis'!I44 -> 0.088 | L156: ='Energy Cost Analysis'!K44 -> 0.092 | M156: ='Energy Cost Analysis'!M44 -> 0.071
D157: Bus Components | E157: =I18/I15 -> 40000 | G157: Cooling Hardware | H157: =I32/I33 -> 25000 | J157: Nat Gas Existing | K157: ='Energy Cost Analysis'!I45 -> 0.032 | L157: ='Energy Cost Analysis'!K45 -> 0.038 | M157: ='Energy Cost Analysis'!M45 -> 0.04
D158: Space Power | E158: =I54+I22*I48/I43 -> 255354.53 | G158: =I27 -> Nat Gas New Build | H158: =I55 -> 97940.304 | J158: Nat Gas New Build | K158: ='Energy Cost Analysis'!I46 -> 0.077 | L158: ='Energy Cost Analysis'!K46 -> 0.07 | M158: ='Energy Cost Analysis'!M46 -> 0.065
D159: Opex | E159: =I20 -> 30000 | G159: Opex | H159: =I34 -> 90000 | J159: Coal Existing | K159: ='Energy Cost Analysis'!I47 -> 0.073 | L159: ='Energy Cost Analysis'!K47 -> 0.08 | M159: ='Energy Cost Analysis'!M47 -> 0.085
D160: Networking Opp. | E160: =I21 -> 0 | J160: Coal New Build | K160: ='Energy Cost Analysis'!I48 -> 0.122 | L160: ='Energy Cost Analysis'!K48 -> 0.115 | M160: ='Energy Cost Analysis'!M48 -> 0.105
D161: Launch Costs Ex. Power | E161: =I56-I22*I48/I43 -> 422530 | J161: Wind Existing | K161: ='Energy Cost Analysis'!I49 -> 0.035 | L161: ='Energy Cost Analysis'!K49 -> 0.03 | M161: ='Energy Cost Analysis'!M49 -> 0.027
J162: Wind New Build | K162: ='Energy Cost Analysis'!I50 -> 0.029810344 | L162: ='Energy Cost Analysis'!K50 -> 0.025121455 | M162: ='Energy Cost Analysis'!M50 -> 0.021348398
J163: Wind + 4h Battery New Build | K163: ='Energy Cost Analysis'!I51 -> 0.053547829 | L163: ='Energy Cost Analysis'!K51 -> 0.043344397 | M163: ='Energy Cost Analysis'!M51 -> 0.035288245
J164: Hydro Existing | K164: ='Energy Cost Analysis'!I52 -> 0.0318251 | L164: ='Energy Cost Analysis'!K52 -> 0.0318251 | M164: ='Energy Cost Analysis'!M52 -> 0.0304414
J165: Hydro New Build | K165: ='Energy Cost Analysis'!I53 -> 0.098832401 | L165: ='Energy Cost Analysis'!K53 -> 0.098832401 | M165: ='Energy Cost Analysis'!M53 -> 0.094764008
D166: Category | E166: Annual Cost | G166: Category | H166: Annual Cost | J166: Ground Solar (Arizona) New Build | K166: ='Energy Cost Analysis'!I54 -> 0.042951312 | L166: ='Energy Cost Analysis'!K54 -> 0.026646775 | M166: ='Energy Cost Analysis'!M54 -> 0.020273478
...

Sheet Revenue and Profit
D4: Revenue and Profit - Per Watt-Year Scenario Model | E4: Revenue and Profit - Per Watt-Year Scenario Model | F4: Revenue and Profit - Per Watt-Year Scenario Model | G4: Revenue and Profit - Per Watt-Year Scenario Model | H4: Revenue and Profit - Per Watt-Year Scenario Model | I4: Revenue and Profit - Per Watt-Year Scenario Model | J4: Revenue and Profit - Per Watt-Year Scenario Model | K4: Revenue and Profit - Per Watt-Year Scenario Model | L4: Revenue and Profit - Per Watt-Year Scenario Model | M4: Revenue and Profit - Per Watt-Year Scenario Model | N4: Revenue and Profit - Per Watt-Year Scenario Model
D5: Blank yellow cells are user inputs. Derived outputs stay pending until required assumptions are filled. All margins are net margins. | E5: Blank yellow cells are user inputs. Derived outputs stay pending until required assumptions are filled. All margins are net margins. | F5: Blank yellow cells are user inputs. Derived outputs stay pending until required assumptions are filled. All margins are net margins. | G5: Blank yellow cells are user inputs. Derived outputs stay pending until required assumptions are filled. All margins are net margins. | H5: Blank yellow cells are user inputs. Derived outputs stay pending until required assumptions are filled. All margins are net margins. | I5: Blank yellow cells are user inputs. Derived outputs stay pending until required assumptions are filled. All margins are net margins. | J5: Blank yellow cells are user inputs. Derived outputs stay pending until required assumptions are filled. All margins are net margins. | K5: Blank yellow cells are user inputs. Derived outputs stay pending until required assumptions are filled. All margins are net margins. | L5: Blank yellow cells are user inputs. Derived outputs stay pending until required assumptions are filled. All margins are net margins. | M5: Blank yellow cells are user inputs. Derived outputs stay pending until required assumptions are filled. All margins are net margins. | N5: Blank yellow cells are user inputs. Derived outputs stay pending until required assumptions are filled. All margins are net margins.
D8: Linked Cost Input | G8: Unit | I8: Value (2026) | K8: Value (2036) | M8: Value (2051) | N8: Notes
D10: Satellite TCO incl. Launch | G10: $/W-yr | I10: ='TCO Analysis'!I66 -> 16.160664 | K10: ='TCO Analysis'!K66 -> 18.733963 | M10: ='TCO Analysis'!M66 -> 40.812947 | N10: Linked from TCO Analysis: satellite TCO incl. launch.
D11: Terrestrial TCO | G11: $/W-yr | I11: ='TCO Analysis'!I69 -> 7.8556084 | K11: ='TCO Analysis'!K69 -> 13.841549 | M11: ='TCO Analysis'!M69 -> 31.853564 | N11: Linked from TCO Analysis: terrestrial datacenter TCO.
D12: Terrestrial IT Hardware Cost | G12: $/W-yr | I12: =('TCO Analysis'!I35/'TCO Analysis'!I36)/('TCO Analysis'!I28*1000) -> 5.9090909 | K12: =('TCO Analysis'!K35/'TCO Analysis'!K36)/('TCO Analysis'!K28*1000) -> 12.121212 | M12: =('TCO Analysis'!M35/'TCO Analysis'!M36)/('TCO Analysis'!M28*1000) -> 30.30303 | N12: Annualized terrestrial IT hardware cost divided by rack IT watts.
D13: Terrestrial Power Source | G13: source | I13: ='TCO Analysis'!I27 -> Nat Gas New Build | K13: ='TCO Analysis'!K27 -> Nat Gas New Build | M13: ='TCO Analysis'!M27 -> Nat Gas New Build | N13: Selected power source from TCO Analysis.
D14: Output Basis | G14: basis | I14: per watt-year | K14: per watt-year | M14: per watt-year | N14: All revenue, expense, and profit rows are shown per watt-year.
D18: xAI + Space Datacenter vs Frontier Lab + Hyperscaler
D19: Assumption / Metric | G19: Unit | I19: Value (2026) | K19: Value (2036) | M19: Value (2051) | N19: Notes
D20: Frontier Lab Net Margin | G20: % | I20: -0.7 | K20: 0.1 | M20: 0.3 | N20: User input; net margin, not gross margin.
D21: Cloud Provider Net Margin | G21: % | I21: 0.3 | K21: 0.3 | M21: 0.3 | N21: User input; net margin for hyperscaler/cloud provider. It affects the frontier lab revenue benchmark, but xAI still does not pay hyperscaler expense.
D22: xAI Revenue Multiplier vs Frontier Lab | G22: x | I22: 1 | K22: 1 | M22: 1 | N22: User input; xAI revenue per W-year vs frontier lab revenue after hyperscaler/cloud markup.
D24: Status | G24: status | I24: =IF(OR(ISBLANK(I20),ISBLANK(I21),ISBLANK(I22),I20>=1,I21>=1),"Inputs pending","Ready") -> Ready | K24: =IF(OR(ISBLANK(K20),ISBLANK(K21),ISBLANK(K22),K20>=1,K21>=1),"Inputs pending","Ready") -> Ready | M24: =IF(OR(ISBLANK(M20),ISBLANK(M21),ISBLANK(M22),M20>=1,M21>=1),"Inputs pending","Ready") -> Ready | N24: Ready once all section inputs are filled and margins are below 100%.
D25: Cloud Inference Price | G25: $/W-yr | I25: =IF(I24<>"Ready","Inputs pending",I11/(1-I21)) -> 11.222298 | K25: =IF(K24<>"Ready","Inputs pending",K11/(1-K21)) -> 19.773641 | M25: =IF(M24<>"Ready","Inputs pending",M11/(1-M21)) -> 45.505091 | N25: Price paid by the frontier lab to the hyperscaler/cloud provider.
D26: Frontier Lab Revenue | G26: $/W-yr | I26: =IF(I24<>"Ready","Inputs pending",I25/(1-I20)) -> 6.6013516 | K26: =IF(K24<>"Ready","Inputs pending",K25/(1-K20)) -> 21.970713 | M26: =IF(M24<>"Ready","Inputs pending",M25/(1-M20)) -> 65.007273 | N26: End-customer frontier lab revenue after paying hyperscaler/cloud costs and lab net margin.
D27: Frontier Lab Expense | G27: $/W-yr | I27: =IF(I24<>"Ready","Inputs pending",I25) -> 11.222298 | K27: =IF(K24<>"Ready","Inputs pending",K25) -> 19.773641 | M27: =IF(M24<>"Ready","Inputs pending",M25) -> 45.505091 | N27: Inference spend paid to hyperscaler/cloud provider.
D28: Frontier Lab Profit | G28: $/W-yr | I28: =IF(I24<>"Ready","Inputs pending",I26-I27) -> -4.6209461 | K28: =IF(K24<>"Ready","Inputs pending",K26-K27) -> 2.1970713 | M28: =IF(M24<>"Ready","Inputs pending",M26-M27) -> 19.502182 | N28: Revenue less inference spend.
D29: xAI + Space Datacenter Revenue | G29: $/W-yr | I29: =IF(I24<>"Ready","Inputs pending",I26*I22) -> 6.6013516 | K29: =IF(K24<>"Ready","Inputs pending",K26*K22) -> 21.970713 | M29: =IF(M24<>"Ready","Inputs pending",M26*M22) -> 65.007273 | N29: xAI revenue equals frontier lab revenue times the xAI multiplier; hyperscaler margin affects market revenue, not xAI expense.
D30: xAI + Space Datacenter Expense | G30: $/W-yr | I30: =IF(I24<>"Ready","Inputs pending",I10) -> 16.160664 | K30: =IF(K24<>"Ready","Inputs pending",K10) -> 18.733963 | M30: =IF(M24<>"Ready","Inputs pending",M10) -> 40.812947 | N30: Satellite TCO incl. launch.
D31: xAI + Space Datacenter Profit | G31: $/W-yr | I31: =IF(I24<>"Ready","Inputs pending",I29-I30) -> -9.559312 | K31: =IF(K24<>"Ready","Inputs pending",K29-K30) -> 3.2367496 | M31: =IF(M24<>"Ready","Inputs pending",M29-M30) -> 24.194327 | N31: Revenue less satellite TCO.
D32: xAI + Space Datacenter Profit Advantage | G32: $/W-yr | I32: =IF(I24<>"Ready","Inputs pending",I31-I28) -> -4.9383659 | K32: =IF(K24<>"Ready","Inputs pending",K31-K28) -> 1.0396783 | M32: =IF(M24<>"Ready","Inputs pending",M31-M28) -> 4.6921446 | N32: xAI profit less frontier lab profit.
D36: xAI + Space Datacenter vs Surveillance Network Space Datacenter
D37: Assumption / Metric | G37: Unit | I37: Value (2026) | K37: Value (2036) | M37: Value (2051) | N37: Notes
D38: Surveillance Revenue Multiplier vs xAI | G38: x | I38: 3 | N38: User input; surveillance network revenue per W-year vs xAI.
D40: Status | G40: status | I40: =IF(OR(ISBLANK(I38),I24<>"Ready"),"Inputs pending","Ready") -> Ready | K40: =IF(OR(ISBLANK(K38),K24<>"Ready"),"Inputs pending","Ready") -> Inputs pending | M40: =IF(OR(ISBLANK(M38),M24<>"Ready"),"Inputs pending","Ready") -> Inputs pending | N40: Ready once Section 1 and surveillance multiplier are filled.
D41: xAI + Space Datacenter Revenue | G41: $/W-yr | I41: =IF(I40<>"Ready","Inputs pending",I29) -> 6.6013516 | K41: =IF(K40<>"Ready","Inputs pending",K29) -> Inputs pending | M41: =IF(M40<>"Ready","Inputs pending",M29) -> Inputs pending | N41: Reuses Section 1 xAI revenue.
D42: xAI + Space Datacenter Expense | G42: $/W-yr | I42: =IF(I40<>"Ready","Inputs pending",I30) -> 16.160664 | K42: =IF(K40<>"Ready","Inputs pending",K30) -> Inputs pending | M42: =IF(M40<>"Ready","Inputs pending",M30) -> Inputs pending | N42: Satellite TCO incl. launch.
D43: xAI + Space Datacenter Profit | G43: $/W-yr | I43: =IF(I40<>"Ready","Inputs pending",I31) -> -9.559312 | K43: =IF(K40<>"Ready","Inputs pending",K31) -> Inputs pending | M43: =IF(M40<>"Ready","Inputs pending",M31) -> Inputs pending | N43: Reuses Section 1 xAI profit.
D44: Surveillance Network Revenue | G44: $/W-yr | I44: =IF(I40<>"Ready","Inputs pending",I41*I38) -> 19.804055 | K44: =IF(K40<>"Ready","Inputs pending",K41*K38) -> Inputs pending | M44: =IF(M40<>"Ready","Inputs pending",M41*M38) -> Inputs pending | N44: xAI revenue times surveillance revenue multiplier.
D45: Surveillance Network Expense | G45: $/W-yr | I45: =IF(I40<>"Ready","Inputs pending",I10) -> 16.160664 | K45: =IF(K40<>"Ready","Inputs pending",K10) -> Inputs pending | M45: =IF(M40<>"Ready","Inputs pending",M10) -> Inputs pending | N45: Satellite TCO incl. launch.
D46: Surveillance Network Profit | G46: $/W-yr | I46: =IF(I40<>"Ready","Inputs pending",I44-I45) -> 3.6433912 | K46: =IF(K40<>"Ready","Inputs pending",K44-K45) -> Inputs pending | M46: =IF(M40<>"Ready","Inputs pending",M44-M45) -> Inputs pending | N46: Revenue less satellite TCO.
D47: Surveillance Profit Advantage | G47: $/W-yr | I47: =IF(I40<>"Ready","Inputs pending",I46-I43) -> 13.202703 | K47: =IF(K40<>"Ready","Inputs pending",K46-K43) -> Inputs pending | M47: =IF(M40<>"Ready","Inputs pending",M46-M43) -> Inputs pending | N47: Surveillance profit less xAI profit.
D52: 3. xAI + Custom Silicon vs Cloud Provider (Nvidia COGS)
D53: Assumption / Metric | G53: Unit | I53: Value (2026) | K53: Value (2036) | M53: Value (2051) | N53: Notes
D54: Cloud Provider Net Margin | G54: % | I54: 0.3 | K54: 0.3 | M54: 0.3 | N54: User input; cloud provider net margin.
D55: Nvidia Net Margin | G55: % | I55: 0.55 | K55: 0.55 | M55: 0.55 | N55: User input; Nvidia net margin.
D56: Custom Silicon Revenue-per-IT-Cost Multiplier | G56: x | I56: 1.05 | K56: 0.65 | M56: 0.6 | N56: User input; custom silicon revenue per IT-cost dollar vs Nvidia.
D58: Status | G58: status | I58: =IF(OR(ISBLANK(I54),ISBLANK(I55),ISBLANK(I56),I54>=1,I55>=1),"Inputs pending","Ready") -> Ready | K58: =IF(OR(ISBLANK(K54),ISBLANK(K55),ISBLANK(K56),K54>=1,K55>=1),"Inputs pending","Ready") -> Ready | M58: =IF(OR(ISBLANK(M54),ISBLANK(M55),ISBLANK(M56),M54>=1,M55>=1),"Inputs pending","Ready") -> Ready | N58: Ready once section inputs are filled and margins are below 100%.
D59: Cloud Provider Revenue | G59: $/W-yr | I59: =IF(I58<>"Ready","Inputs pending",I64/(1-I54)) -> 15.865155 | K59: =IF(K58<>"Ready","Inputs pending",K64/(1-K54)) -> 29.297451 | M59: =IF(M58<>"Ready","Inputs pending",M64/(1-M54)) -> 69.314615 | N59: Supplier-inclusive terrestrial TCO grossed up by cloud provider net margin.
D60: Cloud Provider Profit at Selected Margin | G60: $/W-yr | I60: =IF(I58<>"Ready","Inputs pending",I59*I54) -> 4.7595464 | K60: =IF(K58<>"Ready","Inputs pending",K59*K54) -> 8.7892353 | M60: =IF(M58<>"Ready","Inputs pending",M59*M54) -> 20.794385 | N60: Cloud profit equals cloud revenue times the selected cloud provider net margin.
D61: Nvidia Hardware Spend | G61: $/W-yr | I61: =IF(I58<>"Ready","Inputs pending",I12) -> 5.9090909 | K61: =IF(K58<>"Ready","Inputs pending",K12) -> 12.121212 | M61: =IF(M58<>"Ready","Inputs pending",M12) -> 30.30303 | N61: Annualized terrestrial IT hardware cost per W-year.
D62: Nvidia Margin Burden | G62: $/W-yr | I62: =IF(I58<>"Ready","Inputs pending",I61*I55) -> 3.25 | K62: =IF(K58<>"Ready","Inputs pending",K61*K55) -> 6.6666667 | M62: =IF(M58<>"Ready","Inputs pending",M61*M55) -> 16.666667 | N62: Nvidia net margin embedded in hardware spend; raises the market revenue benchmark.
D63: Cloud Provider Profit | G63: $/W-yr | I63: =IF(I58<>"Ready","Inputs pending",I59*I54) -> 4.7595464 | K63: =IF(K58<>"Ready","Inputs pending",K59*K54) -> 8.7892353 | M63: =IF(M58<>"Ready","Inputs pending",M59*M54) -> 20.794385 | N63: Cloud provider profit using the selected cloud net margin.
D64: Cloud Provider Expense incl. Nvidia | G64: $/W-yr | I64: =IF(I58<>"Ready","Inputs pending",I11+I62) -> 11.105608 | K64: =IF(K58<>"Ready","Inputs pending",K11+K62) -> 20.508216 | M64: =IF(M58<>"Ready","Inputs pending",M11+M62) -> 48.520231 | N64: Terrestrial TCO plus Nvidia margin burden.
D65: xAI Custom Silicon Revenue | G65: $/W-yr | I65: =IF(I58<>"Ready","Inputs pending",I59*I56) -> 16.658413 | K65: =IF(K58<>"Ready","Inputs pending",K59*K56) -> 19.043343 | M65: =IF(M58<>"Ready","Inputs pending",M59*M56) -> 41.588769 | N65: Supplier-inclusive cloud revenue times custom silicon revenue-per-IT-cost multiplier.
D66: xAI Custom Silicon Expense | G66: $/W-yr | I66: =IF(I58<>"Ready","Inputs pending",I10) -> 16.160664 | K66: =IF(K58<>"Ready","Inputs pending",K10) -> 18.733963 | M66: =IF(M58<>"Ready","Inputs pending",M10) -> 40.812947 | N66: Satellite TCO incl. launch.
D67: xAI Custom Silicon Profit | G67: $/W-yr | I67: =IF(I58<>"Ready","Inputs pending",I65-I66) -> 0.49774903 | K67: =IF(K58<>"Ready","Inputs pending",K65-K66) -> 0.30938004 | M67: =IF(M58<>"Ready","Inputs pending",M65-M66) -> 0.77582234 | N67: Revenue less satellite TCO.
D68: xAI Custom Profit Advantage vs Cloud | G68: $/W-yr | I68: =IF(I58<>"Ready","Inputs pending",I67-I63) -> -4.2617974 | K68: =IF(K58<>"Ready","Inputs pending",K67-K63) -> -8.4798552 | M68: =IF(M58<>"Ready","Inputs pending",M67-M63) -> -20.018562 | N68: xAI custom-silicon profit less cloud-provider profit.
D74: 4. SpaceX Full Stack vs Cloud Provider (Nvidia + TSMC COGS)
D75: Assumption / Metric | G75: Unit | I75: Value (2026) | K75: Value (2036) | M75: Value (2051) | N75: Notes
D76: Cloud Provider Net Margin | G76: % | I76: 0.3 | K76: 0.3 | M76: 0.3 | N76: User input; cloud provider net margin.
D77: Nvidia Net Margin | G77: % | I77: 0.55 | K77: 0.55 | M77: 0.55 | N77: User input; Nvidia net margin.
D78: TSMC Net Margin | G78: % | I78: 0.4 | K78: 0.4 | M78: 0.4 | N78: User input; TSMC net margin.
D79: SpaceX Revenue-per-IT-Cost Multiplier | G79: x | I79: 0.95 | K79: 0.6 | M79: 0.55 | N79: User input; SpaceX revenue per IT-cost dollar, same type of multiplier as Section 3.
D81: Status | G81: status | I81: =IF(OR(ISBLANK(I76),ISBLANK(I77),ISBLANK(I78),ISBLANK(I79),I76>=1,I77>=1,I78>=1),"Inputs pending","Ready") -> Ready | K81: =IF(OR(ISBLANK(K76),ISBLANK(K77),ISBLANK(K78),ISBLANK(K79),K76>=1,K77>=1,K78>=1),"Inputs pending","Ready") -> Ready | M81: =IF(OR(ISBLANK(M76),ISBLANK(M77),ISBLANK(M78),ISBLANK(M79),M76>=1,M77>=1,M78>=1),"Inputs pending","Ready") -> Ready | N81: Ready once section inputs are filled and margins are below 100%.
D82: Cloud Provider Revenue | G82: $/W-yr | I82: =IF(I81<>"Ready","Inputs pending",I89/(1-I76)) -> 17.384635 | K82: =IF(K81<>"Ready","Inputs pending",K89/(1-K76)) -> 32.414334 | M82: =IF(M81<>"Ready","Inputs pending",M89/(1-M76)) -> 77.106823 | N82: Supplier-inclusive terrestrial TCO grossed up by cloud provider net margin.
D83: Cloud Provider Profit at Selected Margin | G83: $/W-yr | I83: =IF(I81<>"Ready","Inputs pending",I82*I76) -> 5.2153906 | K83: =IF(K81<>"Ready","Inputs pending",K82*K76) -> 9.7243002 | M83: =IF(M81<>"Ready","Inputs pending",M82*M76) -> 23.132047 | N83: Cloud profit equals cloud revenue times the selected cloud provider net margin.
D84: Nvidia Hardware Spend | G84: $/W-yr | I84: =IF(I81<>"Ready","Inputs pending",I12) -> 5.9090909 | K84: =IF(K81<>"Ready","Inputs pending",K12) -> 12.121212 | M84: =IF(M81<>"Ready","Inputs pending",M12) -> 30.30303 | N84: Annualized terrestrial IT hardware cost per W-year.
D85: Nvidia Margin Burden | G85: $/W-yr | I85: =IF(I81<>"Ready","Inputs pending",I84*I77) -> 3.25 | K85: =IF(K81<>"Ready","Inputs pending",K84*K77) -> 6.6666667 | M85: =IF(M81<>"Ready","Inputs pending",M84*M77) -> 16.666667 | N85: Nvidia net margin embedded in hardware spend; raises the market revenue benchmark.
D86: TSMC Revenue Proxy | G86: $/W-yr | I86: =IF(I81<>"Ready","Inputs pending",I84*(1-I77)) -> 2.6590909 | K86: =IF(K81<>"Ready","Inputs pending",K84*(1-K77)) -> 5.4545455 | M86: =IF(M81<>"Ready","Inputs pending",M84*(1-M77)) -> 13.636364 | N86: Nvidia post-margin expense used as the TSMC-stage revenue proxy.
D87: TSMC Margin Burden | G87: $/W-yr | I87: =IF(I81<>"Ready","Inputs pending",I86*I78) -> 1.0636364 | K87: =IF(K81<>"Ready","Inputs pending",K86*K78) -> 2.1818182 | M87: =IF(M81<>"Ready","Inputs pending",M86*M78) -> 5.4545455 | N87: TSMC net margin embedded in the silicon supply chain; raises the market revenue benchmark.
D88: Cloud Provider Profit | G88: $/W-yr | I88: =IF(I81<>"Ready","Inputs pending",I82*I76) -> 5.2153906 | K88: =IF(K81<>"Ready","Inputs pending",K82*K76) -> 9.7243002 | M88: =IF(M81<>"Ready","Inputs pending",M82*M76) -> 23.132047 | N88: Cloud provider profit using the selected cloud net margin.
D89: Cloud Provider Expense incl. Nvidia + TSMC | G89: $/W-yr | I89: =IF(I81<>"Ready","Inputs pending",I11+I85+I87) -> 12.169245 | K89: =IF(K81<>"Ready","Inputs pending",K11+K85+K87) -> 22.690034 | M89: =IF(M81<>"Ready","Inputs pending",M11+M85+M87) -> 53.974776 | N89: Terrestrial TCO plus Nvidia and TSMC margin burdens.
D90: SpaceX Full-Stack Revenue | G90: $/W-yr | I90: =IF(I81<>"Ready","Inputs pending",I82*I79) -> 16.515404 | K90: =IF(K81<>"Ready","Inputs pending",K82*K79) -> 19.4486 | M90: =IF(M81<>"Ready","Inputs pending",M82*M79) -> 42.408753 | N90: Supplier-inclusive cloud revenue times SpaceX revenue-per-IT-cost multiplier.
D91: SpaceX Full-Stack Expense | G91: $/W-yr | I91: =IF(I81<>"Ready","Inputs pending",I10) -> 16.160664 | K91: =IF(K81<>"Ready","Inputs pending",K10) -> 18.733963 | M91: =IF(M81<>"Ready","Inputs pending",M10) -> 40.812947 | N91: Satellite TCO incl. launch.
D92: SpaceX Full-Stack Profit | G92: $/W-yr | I92: =IF(I81<>"Ready","Inputs pending",I90-I91) -> 0.35474004 | K92: =IF(K81<>"Ready","Inputs pending",K90-K91) -> 0.71463736 | M92: =IF(M81<>"Ready","Inputs pending",M90-M91) -> 1.5958059 | N92: Revenue less satellite TCO.
D93: SpaceX Profit Advantage vs Cloud | G93: $/W-yr | I93: =IF(I81<>"Ready","Inputs pending",I92-I88) -> -4.8606506 | K93: =IF(K81<>"Ready","Inputs pending",K92-K88) -> -9.0096628 | M93: =IF(M81<>"Ready","Inputs pending",M92-M88) -> -21.536241 | N93: SpaceX full-stack profit less cloud-provider profit.
D102: Chart Helper Data | E102: Chart Helper Data | F102: Chart Helper Data | G102: Chart Helper Data | H102: Chart Helper Data | I102: Chart Helper Data | J102: Chart Helper Data | K102: Chart Helper Data | L102: Chart Helper Data | M102: Chart Helper Data | N102: Chart Helper Data
D104: Scenario | E104: Revenue | F104: Expense | G104: Profit | H104: Loss | I104: Scenario | J104: Revenue | K104: Expense | L104: Profit | M104: Loss
D105: =IF(OR(I24="Ready",K24="Ready",M24="Ready"),"","Inputs pending") | E105: =IF(OR(I24="Ready",K24="Ready",M24="Ready"),"",1) | F105: ="" | G105: ="" | H105: ="" | I105: =IF(OR(I40="Ready",K40="Ready",M40="Ready"),"","Inputs pending") | J105: =IF(OR(I40="Ready",K40="Ready",M40="Ready"),"",1) | K105: ="" | L105: ="" | M105: =""
D106: 2026 xAI + Space DC | E106: =IF(I24<>"Ready","",I29) -> 6.6013516 | F106: =IF(I24<>"Ready","",I30) -> 16.160664 | G106: =IF(I24<>"Ready","",IF(I31>0,I31,"")) | H106: =IF(I24<>"Ready","",IF(I31<0,I31,"")) -> -9.559312 | I106: 2026 xAI + Space DC | J106: =IF(I40<>"Ready","",I41) -> 6.6013516 | K106: =IF(I40<>"Ready","",I42) -> 16.160664 | L106: =IF(I40<>"Ready","",IF(I43>0,I43,"")) | M106: =IF(I40<>"Ready","",IF(I43<0,I43,"")) -> -9.559312
D107: 2026 Frontier Lab | E107: =IF(I24<>"Ready","",I26) -> 6.6013516 | F107: =IF(I24<>"Ready","",I27) -> 11.222298 | G107: =IF(I24<>"Ready","",IF(I28>0,I28,"")) | H107: =IF(I24<>"Ready","",IF(I28<0,I28,"")) -> -4.6209461 | I107: 2026 Surveillance | J107: =IF(I40<>"Ready","",I44) -> 19.804055 | K107: =IF(I40<>"Ready","",I45) -> 16.160664 | L107: =IF(I40<>"Ready","",IF(I46>0,I46,"")) -> 3.6433912 | M107: =IF(I40<>"Ready","",IF(I46<0,I46,""))
D108: 2036 xAI + Space DC | E108: =IF(K24<>"Ready","",K29) -> 21.970713 | F108: =IF(K24<>"Ready","",K30) -> 18.733963 | G108: =IF(K24<>"Ready","",IF(K31>0,K31,"")) -> 3.2367496 | H108: =IF(K24<>"Ready","",IF(K31<0,K31,"")) | I108: 2036 xAI + Space DC | J108: =IF(K40<>"Ready","",K41) | K108: =IF(K40<>"Ready","",K42) | L108: =IF(K40<>"Ready","",IF(K43>0,K43,"")) | M108: =IF(K40<>"Ready","",IF(K43<0,K43,""))
D109: 2036 Frontier Lab | E109: =IF(K24<>"Ready","",K26) -> 21.970713 | F109: =IF(K24<>"Ready","",K27) -> 19.773641 | G109: =IF(K24<>"Ready","",IF(K28>0,K28,"")) -> 2.1970713 | H109: =IF(K24<>"Ready","",IF(K28<0,K28,"")) | I109: 2036 Surveillance | J109: =IF(K40<>"Ready","",K44) | K109: =IF(K40<>"Ready","",K45) | L109: =IF(K40<>"Ready","",IF(K46>0,K46,"")) | M109: =IF(K40<>"Ready","",IF(K46<0,K46,""))
D110: 2051 xAI + Space DC | E110: =IF(M24<>"Ready","",M29) -> 65.007273 | F110: =IF(M24<>"Ready","",M30) -> 40.812947 | G110: =IF(M24<>"Ready","",IF(M31>0,M31,"")) -> 24.194327 | H110: =IF(M24<>"Ready","",IF(M31<0,M31,"")) | I110: 2051 xAI + Space DC | J110: =IF(M40<>"Ready","",M41) | K110: =IF(M40<>"Ready","",M42) | L110: =IF(M40<>"Ready","",IF(M43>0,M43,"")) | M110: =IF(M40<>"Ready","",IF(M43<0,M43,""))
D111: 2051 Frontier Lab | E111: =IF(M24<>"Ready","",M26) -> 65.007273 | F111: =IF(M24<>"Ready","",M27) -> 45.505091 | G111: =IF(M24<>"Ready","",IF(M28>0,M28,"")) -> 19.502182 | H111: =IF(M24<>"Ready","",IF(M28<0,M28,"")) | I111: 2051 Surveillance | J111: =IF(M40<>"Ready","",M44) | K111: =IF(M40<>"Ready","",M45) | L111: =IF(M40<>"Ready","",IF(M46>0,M46,"")) | M111: =IF(M40<>"Ready","",IF(M46<0,M46,""))
D114: Scenario | E114: Revenue | F114: Expense | G114: Profit | H114: Loss | I114: Scenario | J114: Revenue | K114: Expense | L114: Profit | M114: Loss
D115: =IF(OR(I58="Ready",K58="Ready",M58="Ready"),"","Inputs pending") | E115: =IF(OR(I58="Ready",K58="Ready",M58="Ready"),"",1) | F115: ="" | G115: ="" | H115: ="" | I115: =IF(OR(I81="Ready",K81="Ready",M81="Ready"),"","Inputs pending") | J115: =IF(OR(I81="Ready",K81="Ready",M81="Ready"),"",1) | K115: ="" | L115: ="" | M115: =""
D116: 2026 xAI Custom | E116: =IF(I58<>"Ready","",I65) -> 16.658413 | F116: =IF(I58<>"Ready","",I66) -> 16.160664 | G116: =IF(I58<>"Ready","",IF(I67>0,I67,"")) -> 0.49774903 | H116: =IF(I58<>"Ready","",IF(I67<0,I67,"")) | I116: 2026 SpaceX | J116: =IF(I81<>"Ready","",I90) -> 16.515404 | K116: =IF(I81<>"Ready","",I91) -> 16.160664 | L116: =IF(I81<>"Ready","",IF(I92>0,I92,"")) -> 0.35474004 | M116: =IF(I81<>"Ready","",IF(I92<0,I92,""))
D117: 2026 Cloud Provider | E117: =IF(I58<>"Ready","",I59) -> 15.865155 | F117: =IF(I58<>"Ready","",I64) -> 11.105608 | G117: =IF(I58<>"Ready","",IF(I63>0,I63,"")) -> 4.7595464 | H117: =IF(I58<>"Ready","",IF(I63<0,I63,"")) | I117: 2026 Cloud Provider | J117: =IF(I81<>"Ready","",I82) -> 17.384635 | K117: =IF(I81<>"Ready","",I89) -> 12.169245 | L117: =IF(I81<>"Ready","",IF(I88>0,I88,"")) -> 5.2153906 | M117: =IF(I81<>"Ready","",IF(I88<0,I88,""))
D118: 2036 xAI Custom | E118: =IF(K58<>"Ready","",K65) -> 19.043343 | F118: =IF(K58<>"Ready","",K66) -> 18.733963 | G118: =IF(K58<>"Ready","",IF(K67>0,K67,"")) -> 0.30938004 | H118: =IF(K58<>"Ready","",IF(K67<0,K67,"")) | I118: 2036 SpaceX | J118: =IF(K81<>"Ready","",K90) -> 19.4486 | K118: =IF(K81<>"Ready","",K91) -> 18.733963 | L118: =IF(K81<>"Ready","",IF(K92>0,K92,"")) -> 0.71463736 | M118: =IF(K81<>"Ready","",IF(K92<0,K92,""))
D119: 2036 Cloud Provider | E119: =IF(K58<>"Ready","",K59) -> 29.297451 | F119: =IF(K58<>"Ready","",K64) -> 20.508216 | G119: =IF(K58<>"Ready","",IF(K63>0,K63,"")) -> 8.7892353 | H119: =IF(K58<>"Ready","",IF(K63<0,K63,"")) | I119: 2036 Cloud Provider | J119: =IF(K81<>"Ready","",K82) -> 32.414334 | K119: =IF(K81<>"Ready","",K89) -> 22.690034 | L119: =IF(K81<>"Ready","",IF(K88>0,K88,"")) -> 9.7243002 | M119: =IF(K81<>"Ready","",IF(K88<0,K88,""))
D120: 2051 xAI Custom | E120: =IF(M58<>"Ready","",M65) -> 41.588769 | F120: =IF(M58<>"Ready","",M66) -> 40.812947 | G120: =IF(M58<>"Ready","",IF(M67>0,M67,"")) -> 0.77582234 | H120: =IF(M58<>"Ready","",IF(M67<0,M67,"")) | I120: 2051 SpaceX | J120: =IF(M81<>"Ready","",M90) -> 42.408753 | K120: =IF(M81<>"Ready","",M91) -> 40.812947 | L120: =IF(M81<>"Ready","",IF(M92>0,M92,"")) -> 1.5958059 | M120: =IF(M81<>"Ready","",IF(M92<0,M92,""))
D121: 2051 Cloud Provider | E121: =IF(M58<>"Ready","",M59) -> 69.314615 | F121: =IF(M58<>"Ready","",M64) -> 48.520231 | G121: =IF(M58<>"Ready","",IF(M63>0,M63,"")) -> 20.794385 | H121: =IF(M58<>"Ready","",IF(M63<0,M63,"")) | I121: 2051 Cloud Provider | J121: =IF(M81<>"Ready","",M82) -> 77.106823 | K121: =IF(M81<>"Ready","",M89) -> 53.974776 | L121: =IF(M81<>"Ready","",IF(M88>0,M88,"")) -> 23.132047 | M121: =IF(M81<>"Ready","",IF(M88<0,M88,""))

Sheet Model Detail
A1: Model Detail - Physical Energy and LCOE Logic
A3: Metric | B3: Unit | C3: 2026 | D3: 2036 | E3: 2051 | F3: Notes
A4: Source projection year | B4: year | C4: 2026 | D4: 2036 | E4: 2050 | F4: 2051 uses 2050 endpoint. | H4: Nuclear | I4: Nat Gas | J4: Coal | K4: Wind+BESS | L4: Hydro | M4: Solar+BESS | Q4: Nuclear | R4: Nat Gas | S4: Coal | T4: Hydro
A5: Ground incident energy | B5: kWh/m2/day | C5: ='Energy Cost Analysis'!I10 -> 6.52 | D5: ='Energy Cost Analysis'!K10 -> 6.52 | E5: ='Energy Cost Analysis'!M10 -> 6.52 | F5: Linked from main assumptions. | H5: ='Energy Cost Analysis'!I44 -> 0.088 | I5: ='Energy Cost Analysis'!I46 -> 0.077 | J5: ='Energy Cost Analysis'!I48 -> 0.122 | K5: ='Energy Cost Analysis'!I51 -> 0.053547829 | L5: ='Energy Cost Analysis'!I53 -> 0.098832401 | M5: ='Energy Cost Analysis'!I55 -> 0.09392325 | Q5: ='Energy Cost Analysis'!I43 -> 0.034 | R5: ='Energy Cost Analysis'!I45 -> 0.032 | S5: ='Energy Cost Analysis'!I47 -> 0.073 | T5: ='Energy Cost Analysis'!I52 -> 0.0318251
A6: Solar power advantage | B6: x | C6: =C7/C5 -> 5.0092025 | D6: =D7/D5 -> 5.0092025 | E6: =E7/E5 -> 5.0092025 | F6: Linked from main assumptions. | H6: ='Energy Cost Analysis'!K44 -> 0.092 | I6: ='Energy Cost Analysis'!K46 -> 0.07 | J6: ='Energy Cost Analysis'!K48 -> 0.115 | K6: ='Energy Cost Analysis'!K51 -> 0.043344397 | L6: ='Energy Cost Analysis'!K53 -> 0.098832401 | M6: ='Energy Cost Analysis'!K55 -> 0.066339927 | Q6: ='Energy Cost Analysis'!K43 -> 0.036 | R6: ='Energy Cost Analysis'!K45 -> 0.038 | S6: ='Energy Cost Analysis'!K47 -> 0.08 | T6: ='Energy Cost Analysis'!K52 -> 0.0318251
A7: SSO incident energy | B7: kWh/m2/day | C7: ='Energy Cost Analysis'!I11 -> 32.66 | D7: ='Energy Cost Analysis'!K11 -> 32.66 | E7: ='Energy Cost Analysis'!M11 -> 32.66 | F7: Ground incident x solar power advantage. | H7: ='Energy Cost Analysis'!M44 -> 0.071 | I7: ='Energy Cost Analysis'!M46 -> 0.065 | J7: ='Energy Cost Analysis'!M48 -> 0.105 | K7: ='Energy Cost Analysis'!M51 -> 0.035288245 | L7: ='Energy Cost Analysis'!M53 -> 0.094764008 | M7: ='Energy Cost Analysis'!M55 -> 0.050943173 | Q7: ='Energy Cost Analysis'!M43 -> 0.038 | R7: ='Energy Cost Analysis'!M45 -> 0.04 | S7: ='Energy Cost Analysis'!M47 -> 0.085 | T7: ='Energy Cost Analysis'!M52 -> 0.0304414
A8: PV ILR | B8: DC/AC | C8: 1.34 | D8: 1.34 | E8: 1.34 | F8: ATB utility PV ILR.
A9: PV STC module efficiency | B9: % | C9: ='Energy Cost Analysis'!I25 -> 0.206 | D9: ='Energy Cost Analysis'!K25 -> 0.26 | E9: ='Energy Cost Analysis'!M25 -> 0.28 | F9: Linked from main assumptions.
A10: Area per kWac | B10: m2/kWac | C10: =C8/C9 -> 6.5048544 | D10: =D8/D9 -> 5.1538462 | E10: =E8/E9 -> 4.7857143 | F10: ILR / STC module efficiency.
A11: PV capex | B11: $/kWac | C11: 1432.0088 | D11: 881.15949 | E11: 682.89636 | F11: ATB UtilityPV Class 1 CAPEX.
A12: PV installed system cost | B12: $/m2 | C12: =C11/C10 -> 220.14463 | D12: =D11/D10 -> 170.97124 | E12: =E11/E10 -> 142.69476 | F12: PV capex / area per kWac.
A13: PV FOM | B13: $/kWac-yr | C13: 20.39528 | D13: 14.869318 | E13: 12.763819 | F13: ATB UtilityPV Class 1 fixed O&M.
A14: PV FOM | B14: $/m2-yr | C14: =C13/C10 -> 3.1353937 | D14: =D13/D10 -> 2.8850916 | E14: =E13/E10 -> 2.6670666 | F14: PV FOM / area per kWac.
A15: Ground hot efficiency | B15: % | C15: ='Energy Cost Analysis'!I26 -> 0.18746 | D15: ='Energy Cost Analysis'!K26 -> 0.2366 | E15: ='Energy Cost Analysis'!M26 -> 0.2548 | F15: Linked from main assumptions.
A16: Ground degradation | B16: %/yr | C16: ='Energy Cost Analysis'!I28 -> 0.007 | D16: ='Energy Cost Analysis'!K28 -> 0.005 | E16: ='Energy Cost Analysis'!M28 -> 0.002 | F16: Linked from main assumptions.
A17: Ground avg degradation factor | B17: x | C17: =IF(C16=0,1,(1-(1-C16)^30)/(30*C16)) -> 0.90482908 | D17: =IF(D16=0,1,(1-(1-D16)^30)/(30*D16)) -> 0.93077205 | E17: =IF(E16=0,1,(1-(1-E16)^30)/(30*E16)) -> 0.9715341 | F17: Geometric average over 30-year ATB cost recovery life.
A18: Ground weather/environment factor | B18: x | C18: ='Energy Cost Analysis'!I12 -> 0.9 | D18: ='Energy Cost Analysis'!K12 -> 0.9 | E18: ='Energy Cost Analysis'!M12 -> 0.9 | F18: Linked from key assumptions; captures weather, dust, wind, and other site losses.
A19: Ground annual delivered electricity | B19: kWh/m2-yr | C19: =C5*365*C15*C18*C17 -> 363.29392 | D19: =D5*365*D15*D18*D17 -> 471.67303 | E19: =E5*365*E15*E18*E17 -> 530.20088 | F19: 6.52 x 365 x hot efficiency x weather/environment factor x degradation factor.
A20: PV FCR | B20: %/yr | C20: ='Energy Cost Analysis'!I29 -> 0.056638023 | D20: ='Energy Cost Analysis'!K29 -> 0.056638023 | E20: ='Energy Cost Analysis'!M29 -> 0.056638023 | F20: Linked from main assumptions.
A21: Ground PV calculated LCOE | B21: $/kWh | C21: =(C12*C20+C14)/C19 -> 0.042951312 | D21: =(D12*D20+D14)/D19 -> 0.026646775 | E21: =(E12*E20+E14)/E19 -> 0.020273478 | F21: (capex x FCR + FOM) / annual delivered kWh/m2.
A22: ATB PV benchmark LCOE | B22: $/kWh | C22: 0.035979648 | D22: 0.021796832 | E22: 0.016454862 | F22: Placeholder row overwritten below.
A23: Firm solar battery duration | B23: hours | C23: ='Energy Cost Analysis'!I13 -> 14.4 | D23: ='Energy Cost Analysis'!K13 -> 14.4 | E23: ='Energy Cost Analysis'!M13 -> 14.4 | F23: Daily-shift storage duration for 24/7 constant solar+BESS output.
A24: 4h battery CAPEX reference | B24: $/kW | C24: ='Energy Cost Analysis'!I30 -> 1659.3941 | D24: ='Energy Cost Analysis'!K30 -> 1326.6147 | E24: ='Energy Cost Analysis'!M30 -> 1035.7717 | F24: Linked from main assumptions.
A25: 4h battery CFC reference | B25: $/kW-yr | C25: ='Energy Cost Analysis'!I31 -> 58.498224 | D25: ='Energy Cost Analysis'!K31 -> 46.76683 | E25: ='Energy Cost Analysis'!M31 -> 36.513813 | F25: Linked from main assumptions.
A26: 4h battery FOM reference | B26: $/kW-yr | C26: ='Energy Cost Analysis'!I32 -> 37.522398 | D26: ='Energy Cost Analysis'!K32 -> 29.496197 | E26: ='Energy Cost Analysis'!M32 -> 22.481448 | F26: Linked from main assumptions.
A27: PV annual kWh per kWac | B27: kWh/kWac-yr | C27: =C19*C10 -> 2363.1741 | D27: =D19*D10 -> 2430.9302 | E27: =E19*E10 -> 2537.3899 | F27: Ground annual kWh/m2 x area per kWac.
A28: Firm BESS cost adder on solar | B28: $/kWh | C28: =(C25+C26)*(C23/(4*'Energy Cost Analysis'!I33))/8760 -> 0.046424152 | D28: =(D25+D26)*(D23/(4*'Energy Cost Analysis'!K33))/8760 -> 0.03687173 | E28: =(E25+E26)*(E23/(4*'Energy Cost Analysis'!M33))/8760 -> 0.028523091 | F28: 4-hour ATB battery fixed cost scaled to firm battery duration and RTE.
A29: Ground Solar+Firm Battery calculated LCOE | B29: $/kWh | C29: =C21*(1+(C23/24)*(1/'Energy Cost Analysis'!I33-1))+C28 -> 0.09392325 | D29: =D21*(1+(D23/24)*(1/'Energy Cost Analysis'!K33-1))+D28 -> 0.066339927 | E29: =E21*(1+(E23/24)*(1/'Energy Cost Analysis'!M33-1))+E28 -> 0.050943173 | F29: PV LCOE grossed up for storage losses plus firm BESS cost adder.
A30: Wind new-build LCOE | B30: $/kWh | C30: 0.029810344 | D30: 0.025121455 | E30: 0.021348398 | F30: ATB land-based wind Class 4.
A31: Wind capacity factor | B31: % | C31: 0.46177 | D31: 0.4777398 | E31: 0.48312 | F31: ATB land-based wind Class 4.
A32: BESS cost adder on wind | B32: $/kWh | C32: =(C25+C26)/(C31*8760) -> 0.023737484 | D32: =(D25+D26)/(D31*8760) -> 0.018222943 | E32: =(E25+E26)/(E31*8760) -> 0.013939847 | F32: (battery CFC + FOM) / wind annual kWh per kW.
A33: Wind+BESS calculated LCOE | B33: $/kWh | C33: =C30+C32 -> 0.053547829 | D33: =D30+D32 -> 0.043344397 | E33: =E30+E32 -> 0.035288245 | F33: Wind LCOE + BESS cost adder.
A34: Hydro FOM | B34: $/kW-yr | C34: 92 | D34: 92 | E34: 88 | F34: ATB Hydropower NPD1 FOM.
A35: Hydro CF | B35: % | C35: 0.33 | D35: 0.33 | E35: 0.33 | F35: ATB Hydropower NPD1 CF.
A36: Hydro existing proxy | B36: $/kWh | C36: =C34/(C35*8760) -> 0.0318251 | D36: =D34/(D35*8760) -> 0.0318251 | E36: =E34/(E35*8760) -> 0.0304414 | F36: Hydro FOM / annual kWh per kW.
A37: Existing source 1 | B37: name | C37: Nuclear | D37: Nuclear | E37: Nuclear | F37: Helper block below supplies cheapest existing.
A38: Cheapest existing US LCOE | B38: $/kWh | C38: =MIN('Energy Cost Analysis'!I43,'Energy Cost Analysis'!I45,'Energy Cost Analysis'!I47,'Energy Cost Analysis'!I52) -> 0.0318251 | D38: =MIN('Energy Cost Analysis'!K43,'Energy Cost Analysis'!K45,'Energy Cost Analysis'!K47,'Energy Cost Analysis'!K52) -> 0.0318251 | E38: =MIN('Energy Cost Analysis'!M43,'Energy Cost Analysis'!M45,'Energy Cost Analysis'!M47,'Energy Cost Analysis'!M52) -> 0.0304414 | F38: Minimum of U.S. existing proxies only; excludes standalone wind/solar.
A39: Cheapest new-build US LCOE | B39: $/kWh | C39: =MIN('Energy Cost Analysis'!I44,'Energy Cost Analysis'!I46,'Energy Cost Analysis'!I48,'Energy Cost Analysis'!I51,'Energy Cost Analysis'!I53,'Energy Cost Analysis'!I55) -> 0.053547829 | D39: =MIN('Energy Cost Analysis'!K44,'Energy Cost Analysis'!K46,'Energy Cost Analysis'!K48,'Energy Cost Analysis'!K51,'Energy Cost Analysis'!K53,'Energy Cost Analysis'!K55) -> 0.043344397 | E39: =MIN('Energy Cost Analysis'!M44,'Energy Cost Analysis'!M46,'Energy Cost Analysis'!M48,'Energy Cost Analysis'!M51,'Energy Cost Analysis'!M53,'Energy Cost Analysis'!M55) -> 0.035288245 | F39: Minimum of U.S. new-build LCOE rows only; excludes standalone wind/solar.
A40: Space array cost | B40: $/m2 | C40: ='Energy Cost Analysis'!I14 -> 330 | D40: ='Energy Cost Analysis'!K14 -> 225 | E40: ='Energy Cost Analysis'!M14 -> 214 | F40: Linked from main assumptions.
A41: Space battery requirement | B41: kWh/kW | C41: ='Energy Cost Analysis'!I16 -> 0 | D41: ='Energy Cost Analysis'!K16 -> 0 | E41: ='Energy Cost Analysis'!M16 -> 0 | F41: Linked from main assumptions.
A42: Space battery cost | B42: $/kWh | C42: ='Energy Cost Analysis'!I37 -> 200 | D42: ='Energy Cost Analysis'!K37 -> 110 | E42: ='Energy Cost Analysis'!M37 -> 80 | F42: Linked from main assumptions.
A43: Space panel density | B43: kg/m2 | C43: ='Energy Cost Analysis'!I34 -> 2.3 | D43: ='Energy Cost Analysis'!K34 -> 2 | E43: ='Energy Cost Analysis'!M34 -> 1.8 | F43: Linked from main assumptions.
A44: Space net efficiency | B44: % | C44: ='Energy Cost Analysis'!I35 -> 0.21 | D44: ='Energy Cost Analysis'!K35 -> 0.24 | E44: ='Energy Cost Analysis'!M35 -> 0.26 | F44: Linked from main assumptions.
A45: Space degradation | B45: %/yr | C45: ='Energy Cost Analysis'!I36 -> 0.015 | D45: ='Energy Cost Analysis'!K36 -> 0.01 | E45: ='Energy Cost Analysis'!M36 -> 0.007 | F45: Linked from main assumptions.
A46: Space useful life | B46: years | C46: ='Energy Cost Analysis'!I15 -> 5 | D46: ='Energy Cost Analysis'!K15 -> 30 | E46: ='Energy Cost Analysis'!M15 -> 30 | F46: Linked from main assumptions.
A47: Space avg degradation factor | B47: x | C47: =IF(C45=0,1,(1-(1-C45)^C46)/(C46*C45)) -> 0.97044664 | D47: =IF(D45=0,1,(1-(1-D45)^D46)/(D46*D45)) -> 0.86766542 | E47: =IF(E45=0,1,(1-(1-E45)^E46)/(E46*E45)) -> 0.90482908 | F47: Geometric average over useful life.
A48: Space lifetime delivered electricity | B48: kWh/m2 | C48: =C7*365*C44*C46*C47 -> 12147.027 | D48: =D7*365*D44*D46*D47 -> 74472.14 | E48: =E7*365*E44*E46*E47 -> 84133.741 | F48: SSO incident x 365 x net efficiency x life x degradation factor.
A49: Space battery cost component | B49: $/m2 | C49: =C41*(C7/24*C44)*C42 -> 0 | D49: =D41*(D7/24*D44)*D42 -> 0 | E49: =E41*(E7/24*E44)*E42 -> 0 | F49: Only applies if battery requirement is nonzero.
A50: Space non-launch LCOE | B50: $/kWh | C50: =(C40+C49)/C48 -> 0.027167141 | D50: =(D40+D49)/D48 -> 0.0030212641 | E50: =(E40+E49)/E48 -> 0.0025435693 | F50: Power hardware cost / lifetime SSO delivered electricity.
A51: BE launch vs Arizona firm solar+BESS | B51: $/kg | C51: =MAX(0,('Energy Cost Analysis'!I55-C50)*C48/C43) -> 352.56012 | D51: =MAX(0,('Energy Cost Analysis'!K55-D50)*D48/D43) -> 2357.7382 | E51: =MAX(0,('Energy Cost Analysis'!M55-E50)*E48/E43) -> 2262.2443 | F51: Uses space density and lifetime kWh per m2.
A52: BE launch vs China solar+BESS | B52: $/kg | C52: =MAX(0,('Energy Cost Analysis'!I57-C50)*C48/C43) -> 146.99413 | D52: =MAX(0,('Energy Cost Analysis'!K57-D50)*D48/D43) -> 1339.7067 | E52: =MAX(0,('Energy Cost Analysis'!M57-E50)*E48/E43) -> 1376.8221 | F52: China separate result.
A53: BE launch vs cheapest new-build US | B53: $/kg | C53: =MAX(0,(C39-C50)*C48/C43) -> 139.32475 | D53: =MAX(0,(D39-D50)*D48/D43) -> 1501.475 | E53: =MAX(0,(E39-E50)*E48/E43) -> 1530.5178 | F53: China excluded.
A54: Cheapest new-build US source | B54: name | C54: =INDEX($H$4:$M$4,1,MATCH(C39,$H$5:$M$5,0)) -> Wind+BESS | D54: =INDEX($H$4:$M$4,1,MATCH(D39,$H$6:$M$6,0)) -> Wind+BESS | E54: =INDEX($H$4:$M$4,1,MATCH(E39,$H$7:$M$7,0)) -> Wind+BESS | F54: Helper result.
A55: BE launch vs cheapest existing US | B55: $/kg | C55: =MAX(0,(C38-C50)*C48/C43) -> 24.600156 | D55: =MAX(0,(D38-D50)*D48/D43) -> 1072.5417 | E55: =MAX(0,(E38-E50)*E48/E43) -> 1303.9716 | F55: China/new build excluded.
A56: Cheapest existing US source | B56: name | C56: =INDEX($Q$4:$T$4,1,MATCH(C38,$Q$5:$T$5,0)) -> Hydro | D56: =INDEX($Q$4:$T$4,1,MATCH(D38,$Q$6:$T$6,0)) -> Hydro | E56: =INDEX($Q$4:$T$4,1,MATCH(E38,$Q$7:$T$7,0)) -> Hydro | F56: Helper result.

Sheet Source Facts
A1: Source Facts
A3: Fact ID | B3: Source | C3: URL / Path | D3: Short Quote / Row Excerpt | E3: Used For | F3: Type | G3: Confidence
A4: SF-USER-GROUND | B4: User instruction in this thread | C4: Conversation | D4: change the winter number to 6.52 kWh/m2/day | E4: Ground incident solar resource | F4: User-provided | G4: High
A5: SF-USER-SSO | B5: User instruction in this thread | C5: Conversation | D5: for the SSO it should be 32.66 kWh/m^2/day | E5: SSO incident solar resource | F5: User-provided | G5: High
A6: SF-DERIVED-ADVANTAGE | B6: Derived from user resource inputs | C6: Conversation | D6: 32.66 / 6.52 = 5.009x | E6: Solar power advantage | F6: Derived | G6: High
A7: SF-USER-FIRM-STORAGE | B7: User instruction in this thread | C7: Conversation + local winter analysis | D7: solar + batteries should handle consistent power by itself | E7: Firm solar+BESS storage duration | F7: User-directed model change | G7: Medium
A8: SF-USER-ENV-FACTOR | B8: User instruction in this thread | C8: Conversation | D8: user defined weather/environment degradation factor for weather/dust/wind etc. | E8: Ground weather/environment factor | F8: User-defined model input | G8: Medium
A9: SF-USER-SPACE-COST | B9: User instruction in this thread | C9: Conversation | D9: Key Assumptions... Space Array Hardware Cost | E9: Space array hardware cost | F9: User-defined model input | G9: Medium
A10: SF-USER-SPACE-LIFE | B10: User instruction in this thread | C10: Conversation | D10: Key Assumptions... Space Useful life at each year | E10: Space useful life | F10: User-defined model input | G10: High
A11: SF-USER-SPACE-BATTERY | B11: User instruction in this thread | C11: Conversation | D11: user define Space battery req. as zero | E11: Space battery requirement | F11: User-defined model input | G11: High
A12: SF-SPACE-EFFICIENCY | B12: Analyst estimate from NASA/SpaceX context | C12: Conversation + NASA SmallSat Power | D12: lower efficiency for the space panels since SpaceX mass produces these | E12: Space panel net efficiency | F12: Analyst estimate | G12: Medium
A13: SF-ATB-PV | B13: NREL ATB 2024b Utility-Scale PV | C13: https://atb.nrel.gov/electricity/2024b/utility-scale_pv | D13: ATB uses $/kWAC and ILR of 1.34; degradation rates include 0.7%, 0.5%, 0.2%. | E13: PV CAPEX, FOM, CF, FCR, degradation | F13: Direct dataset + quote | G13: High
A14: SF-DOE-PV | B14: DOE PV System Cost Benchmarks | C14: https://www.energy.gov/cmei/systems/solar-photovoltaic-system-cost-benchmarks | D14: Each module has area 2.57 m2 and rated power 530 watts, corresponding to 20.6%. | E14: 2026 module area/power/efficiency | F14: Direct quote | G14: High
... A26: SF-SUNLIGHT | B26: Local Sunlight_Analysis.html | C26: C:/Users/User/Documents/Web Scripts/Orbital Datacenters/Sunlight_Analysis.html | D26: wh += SOLAR_INPUT_W_M2 * access * incidence * transmittance * dtHours | E26: Cross-check of user energy geometry | F26: Local model source | G26: Medium

Sheet Assumption Audit
A1: Assumption Audit
A3: Cell | B3: Assumption | C3: Year | D3: Value | E3: Unit | F3: Fact ID(s) | G3: Short Quote / Row Excerpt | H3: Rationale | I3: Derivation | J3: Confidence | K3: Formula
A4: I10 | B4: Arizona Ground Incident Solar Resource | C4: 2026 | D4: ='Energy Cost Analysis'!I10 -> 6.52 | E4: kWh/m2/day | F4: SF-USER-GROUND | G4: change the winter number to 6.52 kWh/m2/day | H4: User-provided revised winter incident resource before efficiencies. | I4: User-provided | J4: High
A5: K10 | B5: Arizona Ground Incident Solar Resource | C5: 2036 | D5: ='Energy Cost Analysis'!K10 -> 6.52 | E5: kWh/m2/day | F5: SF-USER-GROUND | G5: change the winter number to 6.52 kWh/m2/day | H5: User-provided revised winter incident resource before efficiencies. | I5: User-provided | J5: High
A6: M10 | B6: Arizona Ground Incident Solar Resource | C6: 2051 | D6: ='Energy Cost Analysis'!M10 -> 6.52 | E6: kWh/m2/day | F6: SF-USER-GROUND | G6: change the winter number to 6.52 kWh/m2/day | H6: User-provided revised winter incident resource before efficiencies. | I6: User-provided | J6: High
A7: I11 | B7: SSO Incident Solar Resource | C7: 2026 | D7: ='Energy Cost Analysis'!I11 -> 32.66 | E7: kWh/m2/day | F7: SF-USER-SSO | G7: for the SSO it should be 32.66 kWh/m^2/day | H7: User-confirmed SSO incident resource before efficiencies. | I7: User-provided | J7: High
A8: K11 | B8: SSO Incident Solar Resource | C8: 2036 | D8: ='Energy Cost Analysis'!K11 -> 32.66 | E8: kWh/m2/day | F8: SF-USER-SSO | G8: for the SSO it should be 32.66 kWh/m^2/day | H8: User-confirmed SSO incident resource before efficiencies. | I8: User-provided | J8: High
A9: M11 | B9: SSO Incident Solar Resource | C9: 2051 | D9: ='Energy Cost Analysis'!M11 -> 32.66 | E9: kWh/m2/day | F9: SF-USER-SSO | G9: for the SSO it should be 32.66 kWh/m^2/day | H9: User-confirmed SSO incident resource before efficiencies. | I9: User-provided | J9: High
A10: Model Detail!C6 | B10: Solar Power Advantage | C10: 2026 | D10: ='Model Detail'!C6 -> 5.0092025 | E10: x | F10: SF-DERIVED-ADVANTAGE | G10: 32.66 / 6.52 = 5.009x | H10: Current SSO/ground resource ratio after revised winter resource. | I10: =SSO incident / ground incident | J10: High | K10: =Model Detail!C7 / Model Detail!C5
A11: Model Detail!D6 | B11: Solar Power Advantage | C11: 2036 | D11: ='Model Detail'!D6 -> 5.0092025 | E11: x | F11: SF-DERIVED-ADVANTAGE | G11: 32.66 / 6.52 = 5.009x | H11: Current SSO/ground resource ratio after revised winter resource. | I11: =SSO incident / ground incident | J11: High | K11: =Model Detail!D7 / Model Detail!D5
A12: Model Detail!E6 | B12: Solar Power Advantage | C12: 2051 | D12: ='Model Detail'!E6 -> 5.0092025 | E12: x | F12: SF-DERIVED-ADVANTAGE | G12: 32.66 / 6.52 = 5.009x | H12: Current SSO/ground resource ratio after revised winter resource. | I12: =SSO incident / ground incident | J12: High | K12: =Model Detail!E7 / Model Detail!E5
A13: I12 | B13: Ground Weather / Environment Factor | C13: 2026 | D13: ='Energy Cost Analysis'!I12 -> 0.9 | E13: x | F13: SF-USER-ENV-FACTOR | G13: user defined weather/environment degradation factor for weather/dust/wind etc. | H13: User-defined weather, dust, wind, and site-loss factor. | I13: User-defined model input | J13: Medium
A14: K12 | B14: Ground Weather / Environment Factor | C14: 2036 | D14: ='Energy Cost Analysis'!K12 -> 0.9 | E14: x | F14: SF-USER-ENV-FACTOR | G14: user defined weather/environment degradation factor for weather/dust/wind etc. | H14: User-defined weather, dust, wind, and site-loss factor. | I14: User-defined model input | J14: Medium
A15: M12 | B15: Ground Weather / Environment Factor | C15: 2051 | D15: ='Energy Cost Analysis'!M12 -> 0.9 | E15: x | F15: SF-USER-ENV-FACTOR | G15: user defined weather/environment degradation factor for weather/dust/wind etc. | H15: User-defined weather, dust, wind, and site-loss factor. | I15: User-defined model input | J15: Medium
A16: I13 | B16: Firm Solar Battery Duration | C16: 2026 | D16: ='Energy Cost Analysis'!I13 -> 14.4 | E16: hours | F16: SF-USER-FIRM-STORAGE; SF-SUNLIGHT | G16: solar + batteries should handle consistent power by itself | wh += SOLAR_INPUT_W_M2 * access * incidence * transmittance * dtHours | H16: Daily-shift storage for 24/7 constant solar+BESS output. | I16: =24 - (40% winter solar collection window * 24) | J16: Medium
A17: K13 | B17: Firm Solar Battery Duration | C17: 2036 | D17: ='Energy Cost Analysis'!K13 -> 14.4 | E17: hours | F17: SF-USER-FIRM-STORAGE; SF-SUNLIGHT | G17: solar + batteries should handle consistent power by itself | wh += SOLAR_INPUT_W_M2 * access * incidence * transmittance * dtHours | H17: Daily-shift storage for 24/7 constant solar+BESS output. | I17: =24 - (40% winter solar collection window * 24) | J17: Medium
A18: M13 | B18: Firm Solar Battery Duration | C18: 2051 | D18: ='Energy Cost Analysis'!M13 -> 14.4 | E18: hours | F18: SF-USER-FIRM-STORAGE; SF-SUNLIGHT | G18: solar + batteries should handle consistent power by itself | wh += SOLAR_INPUT_W_M2 * access * incidence * transmittance * dtHours | H18: Daily-shift storage for 24/7 constant solar+BESS output. | I18: =24 - (40% winter solar collection window * 24) | J18: Medium
A19: I14 | B19: Space Array Hardware Cost | C19: 2026 | D19: ='Energy Cost Analysis'!I14 -> 330 | E19: $/m2 | F19: SF-USER-SPACE-COST; SF-SPACEX; SF-NSE; SF-MCDOWELL | G19: Key Assumptions... Space Array Hardware Cost | V2 Mini has four times the capacity; satellites are deorbited within weeks of end of mission. | V2 Mini manufacturing costs have been driven toward approximately $400,000 per unit. | V2 Mini solar array size listed as 4.1 m x 12.8 m. | H19: User-defined best-case array hardware cost, with SpaceX/Starlink context retained. | I19: User-defined model input | J19: Medium
A20: K14 | B20: Space Array Hardware Cost | C20: 2036 | D20: ='Energy Cost Analysis'!K14 -> 225 | E20: $/m2 | F20: SF-USER-SPACE-COST; SF-SPACEX; SF-NSE; SF-MCDOWELL | G20: Key Assumptions... Space Array Hardware Cost | V2 Mini has four times the capacity; satellites are deorbited within weeks of end of mission. | V2 Mini manufacturing costs have been driven toward approximately $400,000 per unit. | V2 Mini solar array size listed as 4.1 m x 12.8 m. | H20: User-defined best-case array hardware cost, with SpaceX/Starlink context retained. | I20: User-defined model input | J20: Medium
A21: M14 | B21: Space Array Hardware Cost | C21: 2051 | D21: ='Energy Cost Analysis'!M14 -> 214 | E21: $/m2 | F21: SF-USER-SPACE-COST; SF-SPACEX; SF-NSE; SF-MCDOWELL | G21: Key Assumptions... Space Array Hardware Cost | V2 Mini has four times the capacity; satellites are deorbited within weeks of end of mission. | V2 Mini manufacturing costs have been driven toward approximately $400,000 per unit. | V2 Mini solar array size listed as 4.1 m x 12.8 m. | H21: User-defined best-case array hardware cost, with SpaceX/Starlink context retained. | I21: User-defined model input | J21: Medium
A22: I15 | B22: Space Panel Useful Life | C22: 2026 | D22: ='Energy Cost Analysis'!I15 -> 5 | E22: years | F22: SF-USER-SPACE-LIFE; SF-SPACEX | G22: Key Assumptions... Space Useful life at each year | V2 Mini has four times the capacity; satellites are deorbited within weeks of end of mission. | H22: User-defined useful life constrained by refresh/deorbit horizon. | I22: User-defined model input | J22: High
A23: K15 | B23: Space Panel Useful Life | C23: 2036 | D23: ='Energy Cost Analysis'!K15 -> 30 | E23: years | F23: SF-USER-SPACE-LIFE; SF-SPACEX | G23: Key Assumptions... Space Useful life at each year | V2 Mini has four times the capacity; satellites are deorbited within weeks of end of mission. | H23: User-defined useful life constrained by refresh/deorbit horizon. | I23: User-defined model input | J23: High
A24: M15 | B24: Space Panel Useful Life | C24: 2051 | D24: ='Energy Cost Analysis'!M15 -> 30 | E24: years | F24: SF-USER-SPACE-LIFE; SF-SPACEX | G24: Key Assumptions... Space Useful life at each year | V2 Mini has four times the capacity; satellites are deorbited within weeks of end of mission. | H24: User-defined useful life constrained by refresh/deorbit horizon. | I24: User-defined model input | J24: High
A25: I16 | B25: Space Battery Req. | C25: 2026 | D25: ='Energy Cost Analysis'!I16 -> 0 | E25: kWh/kW | F25: SF-USER-SPACE-BATTERY | G25: user define Space battery req. as zero | H25: User-defined SSO base case assumes no battery. | I25: User-defined model input | J25: High
A26: K16 | B26: Space Battery Req. | C26: 2036 | D26: ='Energy Cost Analysis'!K16 -> 0 | E26: kWh/kW | F26: SF-USER-SPACE-BATTERY | G26: user define Space battery req. as zero | H26: User-defined SSO base case assumes no battery. | I26: User-defined model input | J26: High
A27: M16 | B27: Space Battery Req. | C27: 2051 | D27: ='Energy Cost Analysis'!M16 -> 0 | E27: kWh/kW | F27: SF-USER-SPACE-BATTERY | G27: user define Space battery req. as zero | H27: User-defined SSO base case assumes no battery. | I27: User-defined model input | J27: High
A28: I22 | B28: Source Projection Year | C28: 2026 | D28: ='Energy Cost Analysis'!I22 -> 2026 | E28: year | F28: SF-ATB-PV | G28: ATB uses $/kWAC and ILR of 1.34; degradation rates include 0.7%, 0.5%, 0.2%. | H28: Projection endpoint used for each column. | I28: Direct/derived year label | J28: High
A29: K22 | B29: Source Projection Year | C29: 2036 | D29: ='Energy Cost Analysis'!K22 -> 2036 | E29: year | F29: SF-ATB-PV | G29: ATB uses $/kWAC and ILR of 1.34; degradation rates include 0.7%, 0.5%, 0.2%. | H29: Projection endpoint used for each column. | I29: Direct/derived year label | J29: High
A30: M22 | B30: Source Projection Year | C30: 2051 | D30: ='Energy Cost Analysis'!M22 -> 2050 | E30: year | F30: SF-ATB-PV | G30: ATB uses $/kWAC and ILR of 1.34; degradation rates include 0.7%, 0.5%, 0.2%. | H30: Projection endpoint used for each column. | I30: Direct/derived year label | J30: High
A31: I23 | B31: Ground PV Installed System Cost | C31: 2026 | D31: ='Energy Cost Analysis'!I23 -> 220.14463 | E31: $/m2 | F31: SF-ATB-PV; SF-DOE-PV | G31: ATB uses $/kWAC and ILR of 1.34; degradation rates include 0.7%, 0.5%, 0.2%. | Each module has area 2.57 m2 and rated power 530 watts, corresponding to 20.6%. | H31: Converts ATB $/kWac to area basis using ILR and STC efficiency. | I31: =ATB CAPEX $/kWac / (ILR / STC efficiency) | J31: High | K31: ='Model Detail'!C12
A32: K23 | B32: Ground PV Installed System Cost | C32: 2036 | D32: ='Energy Cost Analysis'!K23 -> 170.97124 | E32: $/m2 | F32: SF-ATB-PV; SF-DOE-PV | G32: ATB uses $/kWAC and ILR of 1.34; degradation rates include 0.7%, 0.5%, 0.2%. | Each module has area 2.57 m2 and rated power 530 watts, corresponding to 20.6%. | H32: Converts ATB $/kWac to area basis using ILR and STC efficiency. | I32: =ATB CAPEX $/kWac / (ILR / STC efficiency) | J32: High | K32: ='Model Detail'!D12
A33: M23 | B33: Ground PV Installed System Cost | C33: 2051 | D33: ='Energy Cost Analysis'!M23 -> 142.69476 | E33: $/m2 | F33: SF-ATB-PV; SF-DOE-PV | G33: ATB uses $/kWAC and ILR of 1.34; degradation rates include 0.7%, 0.5%, 0.2%. | Each module has area 2.57 m2 and rated power 530 watts, corresponding to 20.6%. | H33: Converts ATB $/kWac to area basis using ILR and STC efficiency. | I33: =ATB CAPEX $/kWac / (ILR / STC efficiency) | J33: High | K33: ='Model Detail'!E12
A34: I24 | B34: Ground PV Fixed O&M | C34: 2026 | D34: ='Energy Cost Analysis'!I24 -> 3.1353937 | E34: $/m2-yr | F34: SF-ATB-PV | G34: ATB uses $/kWAC and ILR of 1.34; degradation rates include 0.7%, 0.5%, 0.2%. | H34: Converts ATB $/kWac-yr to area basis. | I34: =ATB FOM $/kWac-yr / area per kWac | J34: High | K34: ='Model Detail'!C14
A35: K24 | B35: Ground PV Fixed O&M | C35: 2036 | D35: ='Energy Cost Analysis'!K24 -> 2.8850916 | E35: $/m2-yr | F35: SF-ATB-PV | G35: ATB uses $/kWAC and ILR of 1.34; degradation rates include 0.7%, 0.5%, 0.2%. | H35: Converts ATB $/kWac-yr to area basis. | I35: =ATB FOM $/kWac-yr / area per kWac | J35: High | K35: ='Model Detail'!D14
A36: M24 | B36: Ground PV Fixed O&M | C36: 2051 | D36: ='Energy Cost Analysis'!M24 -> 2.6670666 | E36: $/m2-yr | F36: SF-ATB-PV | G36: ATB uses $/kWAC and ILR of 1.34; degradation rates include 0.7%, 0.5%, 0.2%. | H36: Converts ATB $/kWac-yr to area basis. | I36: =ATB FOM $/kWac-yr / area per kWac | J36: High | K36: ='Model Detail'!E14
A37: I25 | B37: Ground PV STC Module Efficiency | C37: 2026 | D37: ='Energy Cost Analysis'!I25 -> 0.206 | E37: % | F37: SF-DOE-PV; SF-ATB-PV | G37: Each module has area 2.57 m2 and rated power 530 watts, corresponding to 20.6%. | ATB uses $/kWAC and ILR of 1.34; degradation rates include 0.7%, 0.5%, 0.2%. | H37: 2026 direct DOE benchmark; future is analyst estimate from ATB improvement path. | I37: Direct for 2026; analyst for future | J37: Medium
A38: K25 | B38: Ground PV STC Module Efficiency | C38: 2036 | D38: ='Energy Cost Analysis'!K25 -> 0.26 | E38: % | F38: SF-DOE-PV; SF-ATB-PV | G38: Each module has area 2.57 m2 and rated power 530 watts, corresponding to 20.6%. | ATB uses $/kWAC and ILR of 1.34; degradation rates include 0.7%, 0.5%, 0.2%. | H38: 2026 direct DOE benchmark; future is analyst estimate from ATB improvement path. | I38: Direct for 2026; analyst for future | J38: Medium
A39: M25 | B39: Ground PV STC Module Efficiency | C39: 2051 | D39: ='Energy Cost Analysis'!M25 -> 0.28 | E39: % | F39: SF-DOE-PV; SF-ATB-PV | G39: Each module has area 2.57 m2 and rated power 530 watts, corresponding to 20.6%. | ATB uses $/kWAC and ILR of 1.34; degradation rates include 0.7%, 0.5%, 0.2%. | H39: 2026 direct DOE benchmark; future is analyst estimate from ATB improvement path. | I39: Direct for 2026; analyst for future | J39: Medium
A40: I26 | B40: Ground Panel Effective Efficiency @ 55C | C40: 2026 | D40: ='Energy Cost Analysis'!I26 -> 0.18746 | E40: % | F40: SF-DOE-PV; SF-ATB-PV | G40: Each module has area 2.57 m2 and rated power 530 watts, corresponding to 20.6%. | ATB uses $/kWAC and ILR of 1.34; degradation rates include 0.7%, 0.5%, 0.2%. | H40: Applies explicit hot-operation derate to STC efficiency. | I40: =STC efficiency * temperature derate | J40: Medium | K40: =I25*I27
A41: K26 | B41: Ground Panel Effective Efficiency @ 55C | C41: 2036 | D41: ='Energy Cost Analysis'!K26 -> 0.2366 | E41: % | F41: SF-DOE-PV; SF-ATB-PV | G41: Each module has area 2.57 m2 and rated power 530 watts, corresponding to 20.6%. | ATB uses $/kWAC and ILR of 1.34; degradation rates include 0.7%, 0.5%, 0.2%. | H41: Applies explicit hot-operation derate to STC efficiency. | I41: =STC efficiency * temperature derate | J41: Medium | K41: =K25*K27
A42: M26 | B42: Ground Panel Effective Efficiency @ 55C | C42: 2051 | D42: ='Energy Cost Analysis'!M26 -> 0.2548 | E42: % | F42: SF-DOE-PV; SF-ATB-PV | G42: Each module has area 2.57 m2 and rated power 530 watts, corresponding to 20.6%. | ATB uses $/kWAC and ILR of 1.34; degradation rates include 0.7%, 0.5%, 0.2%. | H42: Applies explicit hot-operation derate to STC efficiency. | I42: =STC efficiency * temperature derate | J42: Medium | K42: =M25*M27
A43: I27 | B43: Ground Temperature Derate Factor | C43: 2026 | D43: ='Energy Cost Analysis'!I27 -> 0.91 | E43: x | F43: SF-DOE-PV; SF-ATB-PV | G43: Each module has area 2.57 m2 and rated power 530 watts, corresponding to 20.6%. | ATB uses $/kWAC and ILR of 1.34; degradation rates include 0.7%, 0.5%, 0.2%. | H43: Explicit hot Arizona temperature derate. | I43: Analyst estimate | J43: Medium
A44: K27 | B44: Ground Temperature Derate Factor | C44: 2036 | D44: ='Energy Cost Analysis'!K27 -> 0.91 | E44: x | F44: SF-DOE-PV; SF-ATB-PV | G44: Each module has area 2.57 m2 and rated power 530 watts, corresponding to 20.6%. | ATB uses $/kWAC and ILR of 1.34; degradation rates include 0.7%, 0.5%, 0.2%. | H44: Explicit hot Arizona temperature derate. | I44: Analyst estimate | J44: Medium
A45: M27 | B45: Ground Temperature Derate Factor | C45: 2051 | D45: ='Energy Cost Analysis'!M27 -> 0.91 | E45: x | F45: SF-DOE-PV; SF-ATB-PV | G45: Each module has area 2.57 m2 and rated power 530 watts, corresponding to 20.6%. | ATB uses $/kWAC and ILR of 1.34; degradation rates include 0.7%, 0.5%, 0.2%. | H45: Explicit hot Arizona temperature derate. | I45: Analyst estimate | J45: Medium
A46: I28 | B46: Ground Panel Degradation | C46: 2026 | D46: ='Energy Cost Analysis'!I28 -> 0.007 | E46: %/yr | F46: SF-ATB-PV | G46: ATB uses $/kWAC and ILR of 1.34; degradation rates include 0.7%, 0.5%, 0.2%. | H46: ATB degradation rates. | I46: Direct/ATB pathway | J46: High
A47: K28 | B47: Ground Panel Degradation | C47: 2036 | D47: ='Energy Cost Analysis'!K28 -> 0.005 | E47: %/yr | F47: SF-ATB-PV | G47: ATB uses $/kWAC and ILR of 1.34; degradation rates include 0.7%, 0.5%, 0.2%. | H47: ATB degradation rates. | I47: Direct/ATB pathway | J47: High
A48: M28 | B48: Ground Panel Degradation | C48: 2051 | D48: ='Energy Cost Analysis'!M28 -> 0.002 | E48: %/yr | F48: SF-ATB-PV | G48: ATB uses $/kWAC and ILR of 1.34; degradation rates include 0.7%, 0.5%, 0.2%. | H48: ATB degradation rates. | I48: Direct/ATB pathway | J48: High
A49: I29 | B49: Ground PV Fixed Charge Rate | C49: 2026 | D49: ='Energy Cost Analysis'!I29 -> 0.056638023 | E49: %/yr | F49: SF-ATB-PV | G49: ATB uses $/kWAC and ILR of 1.34; degradation rates include 0.7%, 0.5%, 0.2%. | H49: ATB R&D 30-year FCR. | I49: Direct dataset | J49: High
A50: K29 | B50: Ground PV Fixed Charge Rate | C50: 2036 | D50: ='Energy Cost Analysis'!K29 -> 0.056638023 | E50: %/yr | F50: SF-ATB-PV | G50: ATB uses $/kWAC and ILR of 1.34; degradation rates include 0.7%, 0.5%, 0.2%. | H50: ATB R&D 30-year FCR. | I50: Direct dataset | J50: High
A51: M29 | B51: Ground PV Fixed Charge Rate | C51: 2051 | D51: ='Energy Cost Analysis'!M29 -> 0.056638023 | E51: %/yr | F51: SF-ATB-PV | G51: ATB uses $/kWAC and ILR of 1.34; degradation rates include 0.7%, 0.5%, 0.2%. | H51: ATB R&D 30-year FCR. | I51: Direct dataset | J51: High
A52: I30 | B52: 4h Battery CAPEX Reference | C52: 2026 | D52: ='Energy Cost Analysis'!I30 -> 1659.3941 | E52: $/kW | F52: SF-ATB-BESS | G52: A 4-hour device has expected capacity factor 16.7%; ATB assumes round-trip efficiency of 85%. | H52: ATB 4-hour BESS CAPEX reference for scalable storage cost. | I52: Direct dataset | J52: High
A53: K30 | B53: 4h Battery CAPEX Reference | C53: 2036 | D53: ='Energy Cost Analysis'!K30 -> 1326.6147 | E53: $/kW | F53: SF-ATB-BESS | G53: A 4-hour device has expected capacity factor 16.7%; ATB assumes round-trip efficiency of 85%. | H53: ATB 4-hour BESS CAPEX reference for scalable storage cost. | I53: Direct dataset | J53: High
A54: M30 | B54: 4h Battery CAPEX Reference | C54: 2051 | D54: ='Energy Cost Analysis'!M30 -> 1035.7717 | E54: $/kW | F54: SF-ATB-BESS | G54: A 4-hour device has expected capacity factor 16.7%; ATB assumes round-trip efficiency of 85%. | H54: ATB 4-hour BESS CAPEX reference for scalable storage cost. | I54: Direct dataset | J54: High
A55: I31 | B55: 4h Battery Capital Fixed Cost Reference | C55: 2026 | D55: ='Energy Cost Analysis'!I31 -> 58.498224 | E55: $/kW-yr | F55: SF-ATB-BESS | G55: A 4-hour device has expected capacity factor 16.7%; ATB assumes round-trip efficiency of 85%. | H55: ATB 4-hour BESS capital fixed cost reference; firm case scales by duration. | I55: Direct dataset | J55: High
A56: K31 | B56: 4h Battery Capital Fixed Cost Reference | C56: 2036 | D56: ='Energy Cost Analysis'!K31 -> 46.76683 | E56: $/kW-yr | F56: SF-ATB-BESS | G56: A 4-hour device has expected capacity factor 16.7%; ATB assumes round-trip efficiency of 85%. | H56: ATB 4-hour BESS capital fixed cost reference; firm case scales by duration. | I56: Direct dataset | J56: High
A57: M31 | B57: 4h Battery Capital Fixed Cost Reference | C57: 2051 | D57: ='Energy Cost Analysis'!M31 -> 36.513813 | E57: $/kW-yr | F57: SF-ATB-BESS | G57: A 4-hour device has expected capacity factor 16.7%; ATB assumes round-trip efficiency of 85%. | H57: ATB 4-hour BESS capital fixed cost reference; firm case scales by duration. | I57: Direct dataset | J57: High
A58: I32 | B58: 4h Battery Fixed O&M Reference | C58: 2026 | D58: ='Energy Cost Analysis'!I32 -> 37.522398 | E58: $/kW-yr | F58: SF-ATB-BESS | G58: A 4-hour device has expected capacity factor 16.7%; ATB assumes round-trip efficiency of 85%. | H58: ATB 4-hour BESS fixed O&M reference; firm case scales by duration. | I58: Direct dataset | J58: High
A59: K32 | B59: 4h Battery Fixed O&M Reference | C59: 2036 | D59: ='Energy Cost Analysis'!K32 -> 29.496197 | E59: $/kW-yr | F59: SF-ATB-BESS | G59: A 4-hour device has expected capacity factor 16.7%; ATB assumes round-trip efficiency of 85%. | H59: ATB 4-hour BESS fixed O&M reference; firm case scales by duration. | I59: Direct dataset | J59: High
A60: M32 | B60: 4h Battery Fixed O&M Reference | C60: 2051 | D60: ='Energy Cost Analysis'!M32 -> 22.481448 | E60: $/kW-yr | F60: SF-ATB-BESS | G60: A 4-hour device has expected capacity factor 16.7%; ATB assumes round-trip efficiency of 85%. | H60: ATB 4-hour BESS fixed O&M reference; firm case scales by duration. | I60: Direct dataset | J60: High
A61: I33 | B61: Ground Battery Round-trip Efficiency | C61: 2026 | D61: ='Energy Cost Analysis'!I33 -> 0.85 | E61: % | F61: SF-ATB-BESS | G61: A 4-hour device has expected capacity factor 16.7%; ATB assumes round-trip efficiency of 85%. | H61: ATB representative RTE. | I61: Direct quote | J61: High
A62: K33 | B62: Ground Battery Round-trip Efficiency | C62: 2036 | D62: ='Energy Cost Analysis'!K33 -> 0.85 | E62: % | F62: SF-ATB-BESS | G62: A 4-hour device has expected capacity factor 16.7%; ATB assumes round-trip efficiency of 85%. | H62: ATB representative RTE. | I62: Direct quote | J62: High
A63: M33 | B63: Ground Battery Round-trip Efficiency | C63: 2051 | D63: ='Energy Cost Analysis'!M33 -> 0.85 | E63: % | F63: SF-ATB-BESS | G63: A 4-hour device has expected capacity factor 16.7%; ATB assumes round-trip efficiency of 85%. | H63: ATB representative RTE. | I63: Direct quote | J63: High
A64: I34 | B64: Space Panel Density | C64: 2026 | D64: ='Energy Cost Analysis'!I34 -> 2.3 | E64: kg/m2 | F64: SF-NASA-POWER; SF-MCDOWELL | G64: Space solar arrays seek lower cost and higher production; cells over 32% have higher cost than terrestrial silicon. | V2 Mini solar array size listed as 4.1 m x 12.8 m. | H64: Best-case lightweight array density, checked against specific-power context. | I64: Analyst estimate | J64: Medium
A65: K34 | B65: Space Panel Density | C65: 2036 | D65: ='Energy Cost Analysis'!K34 -> 2 | E65: kg/m2 | F65: SF-NASA-POWER; SF-MCDOWELL | G65: Space solar arrays seek lower cost and higher production; cells over 32% have higher cost than terrestrial silicon. | V2 Mini solar array size listed as 4.1 m x 12.8 m. | H65: Best-case lightweight array density, checked against specific-power context. | I65: Analyst estimate | J65: Medium
A66: M34 | B66: Space Panel Density | C66: 2051 | D66: ='Energy Cost Analysis'!M34 -> 1.8 | E66: kg/m2 | F66: SF-NASA-POWER; SF-MCDOWELL | G66: Space solar arrays seek lower cost and higher production; cells over 32% have higher cost than terrestrial silicon. | V2 Mini solar array size listed as 4.1 m x 12.8 m. | H66: Best-case lightweight array density, checked against specific-power context. | I66: Analyst estimate | J66: Medium
A67: I35 | B67: Space Panel Net Efficiency @ 95C | C67: 2026 | D67: ='Energy Cost Analysis'!I35 -> 0.21 | E67: % | F67: SF-SPACE-EFFICIENCY; SF-NASA-POWER | G67: lower efficiency for the space panels since SpaceX mass produces these | Space solar arrays seek lower cost and higher production; cells over 32% have higher cost than terrestrial silicon. | H67: Lowered for mass-produced, cost-optimized SpaceX arrays operating hot in LEO. | I67: Analyst estimate | J67: Medium
A68: K35 | B68: Space Panel Net Efficiency @ 95C | C68: 2036 | D68: ='Energy Cost Analysis'!K35 -> 0.24 | E68: % | F68: SF-SPACE-EFFICIENCY; SF-NASA-POWER | G68: lower efficiency for the space panels since SpaceX mass produces these | Space solar arrays seek lower cost and higher production; cells over 32% have higher cost than terrestrial silicon. | H68: Lowered for mass-produced, cost-optimized SpaceX arrays operating hot in LEO. | I68: Analyst estimate | J68: Medium
A69: M35 | B69: Space Panel Net Efficiency @ 95C | C69: 2051 | D69: ='Energy Cost Analysis'!M35 -> 0.26 | E69: % | F69: SF-SPACE-EFFICIENCY; SF-NASA-POWER | G69: lower efficiency for the space panels since SpaceX mass produces these | Space solar arrays seek lower cost and higher production; cells over 32% have higher cost than terrestrial silicon. | H69: Lowered for mass-produced, cost-optimized SpaceX arrays operating hot in LEO. | I69: Analyst estimate | J69: Medium
A70: I36 | B70: Space Panel Degradation | C70: 2026 | D70: ='Energy Cost Analysis'!I36 -> 0.015 | E70: %/yr | F70: SF-NASA-POWER; SF-SPACEX | G70: Space solar arrays seek lower cost and higher production; cells over 32% have higher cost than terrestrial silicon. | V2 Mini has four times the capacity; satellites are deorbited within weeks of end of mission. | H70: Short-life LEO power hardware estimate. | I70: Analyst estimate | J70: Medium
A71: K36 | B71: Space Panel Degradation | C71: 2036 | D71: ='Energy Cost Analysis'!K36 -> 0.01 | E71: %/yr | F71: SF-NASA-POWER; SF-SPACEX | G71: Space solar arrays seek lower cost and higher production; cells over 32% have higher cost than terrestrial silicon. | V2 Mini has four times the capacity; satellites are deorbited within weeks of end of mission. | H71: Short-life LEO power hardware estimate. | I71: Analyst estimate | J71: Medium
A72: M36 | B72: Space Panel Degradation | C72: 2051 | D72: ='Energy Cost Analysis'!M36 -> 0.007 | E72: %/yr | F72: SF-NASA-POWER; SF-SPACEX | G72: Space solar arrays seek lower cost and higher production; cells over 32% have higher cost than terrestrial silicon. | V2 Mini has four times the capacity; satellites are deorbited within weeks of end of mission. | H72: Short-life LEO power hardware estimate. | I72: Analyst estimate | J72: Medium
A73: I37 | B73: Space Battery Storage Cost | C73: 2026 | D73: ='Energy Cost Analysis'!I37 -> 200 | E73: $/kWh | F73: SF-ATB-BESS; SF-NASA-POWER | G73: A 4-hour device has expected capacity factor 16.7%; ATB assumes round-trip efficiency of 85%. | Space solar arrays seek lower cost and higher production; cells over 32% have higher cost than terrestrial silicon. | H73: Unused placeholder while req is zero. | I73: Analyst estimate | J73: Low
A74: K37 | B74: Space Battery Storage Cost | C74: 2036 | D74: ='Energy Cost Analysis'!K37 -> 110 | E74: $/kWh | F74: SF-ATB-BESS; SF-NASA-POWER | G74: A 4-hour device has expected capacity factor 16.7%; ATB assumes round-trip efficiency of 85%. | Space solar arrays seek lower cost and higher production; cells over 32% have higher cost than terrestrial silicon. | H74: Unused placeholder while req is zero. | I74: Analyst estimate | J74: Low
A75: M37 | B75: Space Battery Storage Cost | C75: 2051 | D75: ='Energy Cost Analysis'!M37 -> 80 | E75: $/kWh | F75: SF-ATB-BESS; SF-NASA-POWER | G75: A 4-hour device has expected capacity factor 16.7%; ATB assumes round-trip efficiency of 85%. | Space solar arrays seek lower cost and higher production; cells over 32% have higher cost than terrestrial silicon. | H75: Unused placeholder while req is zero. | I75: Analyst estimate | J75: Low
